{
  "config_id": "R-10",
  "updateIntervalMinutes": {
    "2G": 20,
    "3G": 20,
    "4G": 20,
    "WIFI": 20
  },
  "result": [
    {
      "track_id": "hq_yahoo",
      "title": "Yahoo!",
      "title_icon_url": "",
      "headImageUrl": "",
      "link_type": "app",
      "data": [
        {
          "text": "Yahoo財經大人物",
          "url": "https://tw.news.yahoo.com/topic/CEO-interview",
          "h5_url": "https://tw.news.yahoo.com/topic/CEO-interview",
          "appIconUrl": "",
          "sourceUniqueId": "content_yahoo",
          "package": ""
        },
        {
          "text": "|2026理財心法|",
          "url": "https://tw.news.yahoo.com/%E3%80%90%E7%89%B9%E5%88%A5%E4%BC%81%E7%95%AB%E3%80%91%E6%8E%8C%E6%8F%A1%E5%85%A8%E7%90%83%E5%8C%AF%E7%8E%87%E6%B3%A2%E5%8B%95-2026%E5%AE%B6%E5%BA%AD%E7%90%86%E8%B2%A1%E5%BF%83%E6%B3%95%E5%A4%A7%E6%8F%AD%E5%AF%86-065118315.html",
          "h5_url": "https://tw.news.yahoo.com/%E3%80%90%E7%89%B9%E5%88%A5%E4%BC%81%E7%95%AB%E3%80%91%E6%8E%8C%E6%8F%A1%E5%85%A8%E7%90%83%E5%8C%AF%E7%8E%87%E6%B3%A2%E5%8B%95-2026%E5%AE%B6%E5%BA%AD%E7%90%86%E8%B2%A1%E5%BF%83%E6%B3%95%E5%A4%A7%E6%8F%AD%E5%AF%86-065118315.html",
          "appIconUrl": "",
          "sourceUniqueId": "content_yahoo",
          "package": ""
        },
        {
          "text": "Yahoo Tech",
          "url": "https://tw.news.yahoo.com/yahoo_tech_tw_942--%E6%89%80%E6%9C%89%E9%A1%9E%E5%88%A5/archive",
          "h5_url": "https://tw.news.yahoo.com/yahoo_tech_tw_942--%E6%89%80%E6%9C%89%E9%A1%9E%E5%88%A5/archive",
          "appIconUrl": "",
          "sourceUniqueId": "content_yahoo",
          "package": ""
        },
        {
          "text": "2025搜尋大數據揭密",
          "url": "https://tw.news.yahoo.com/12%E5%80%8B%E6%84%8F%E6%83%B3%E4%B8%8D%E5%88%B0%E5%8F%B0%E7%81%A3%E4%BA%BA%E7%9A%84%E6%90%9C%E5%B0%8B%E8%A1%8C%E7%82%BA-%E6%98%9F%E6%9C%9F%E4%B8%80%E6%83%B3%E9%9B%A2%E8%81%B7%EF%BC%9F%E6%98%9F%E6%9C%9F%E4%BA%8C%E8%A8%82%E6%A9%9F%E7%A5%A8%EF%BC%9F%EF%BD%9Cyahoo-2025%E6%90%9C%E5%B0%8B%E5%A4%A7%E6%95%B8%E6%93%9A%E6%8F%AD%E5%AF%86-020000000.html",
          "h5_url": "https://tw.news.yahoo.com/12%E5%80%8B%E6%84%8F%E6%83%B3%E4%B8%8D%E5%88%B0%E5%8F%B0%E7%81%A3%E4%BA%BA%E7%9A%84%E6%90%9C%E5%B0%8B%E8%A1%8C%E7%82%BA-%E6%98%9F%E6%9C%9F%E4%B8%80%E6%83%B3%E9%9B%A2%E8%81%B7%EF%BC%9F%E6%98%9F%E6%9C%9F%E4%BA%8C%E8%A8%82%E6%A9%9F%E7%A5%A8%EF%BC%9F%EF%BD%9Cyahoo-2025%E6%90%9C%E5%B0%8B%E5%A4%A7%E6%95%B8%E6%93%9A%E6%8F%AD%E5%AF%86-020000000.html",
          "appIconUrl": "",
          "sourceUniqueId": "content_yahoo",
          "package": ""
        },
        {
          "text": "「早就打算不副署」卓已做好準備",
          "url": "https://tw.news.yahoo.com/%E7%8D%A8%E5%AE%B6%E5%B0%88%E8%A8%AA-%E5%BE%9E-%E4%B8%8D%E5%9F%B7%E8%A1%8C-%E5%88%B0-%E4%B8%8D%E5%89%AF%E7%BD%B2-085107424.html",
          "h5_url": "https://tw.news.yahoo.com/%E7%8D%A8%E5%AE%B6%E5%B0%88%E8%A8%AA-%E5%BE%9E-%E4%B8%8D%E5%9F%B7%E8%A1%8C-%E5%88%B0-%E4%B8%8D%E5%89%AF%E7%BD%B2-085107424.html",
          "appIconUrl": "",
          "sourceUniqueId": "content_yahoo",
          "package": ""
        },
        {
          "text": "7理由 高院改判高虹安貪污無罪",
          "url": "https://tw.news.yahoo.com/%E7%82%BA%E4%BD%95%E9%AB%98%E8%99%B9%E5%AE%89%E8%B2%AA%E6%B1%A1%E9%83%A8%E5%88%86%E7%84%A1%E7%BD%AA-%E9%AB%98%E9%99%A2%E5%88%977%E7%90%86%E7%94%B1-%E5%8A%A9%E7%90%86%E8%B2%BB%E7%82%BA-%E5%AF%A6%E8%B3%AA%E8%A3%9C%E5%8A%A9-%E5%BD%88%E6%80%A7%E5%8B%BB%E7%94%A8-074141251.html",
          "h5_url": "https://tw.news.yahoo.com/%E7%82%BA%E4%BD%95%E9%AB%98%E8%99%B9%E5%AE%89%E8%B2%AA%E6%B1%A1%E9%83%A8%E5%88%86%E7%84%A1%E7%BD%AA-%E9%AB%98%E9%99%A2%E5%88%977%E7%90%86%E7%94%B1-%E5%8A%A9%E7%90%86%E8%B2%BB%E7%82%BA-%E5%AF%A6%E8%B3%AA%E8%A3%9C%E5%8A%A9-%E5%BD%88%E6%80%A7%E5%8B%BB%E7%94%A8-074141251.html",
          "appIconUrl": "",
          "sourceUniqueId": "content_yahoo",
          "package": ""
        },
        {
          "text": "入夜急凍 明天清晨低溫探11℃",
          "url": "https://tw.news.yahoo.com/%E6%98%8E%E5%A4%A9%E5%A4%A9%E6%B0%A3%E6%B8%85%E6%99%A8%E4%BD%8E%E6%BA%AB%E6%8E%A211%E2%84%83-%E5%8C%97%E5%8C%97%E5%9F%BA%E5%AE%9C%E7%95%99%E6%84%8F%E8%BC%83%E5%A4%A7%E9%9B%A8%E5%8B%A2-101509154.html",
          "h5_url": "https://tw.news.yahoo.com/%E6%98%8E%E5%A4%A9%E5%A4%A9%E6%B0%A3%E6%B8%85%E6%99%A8%E4%BD%8E%E6%BA%AB%E6%8E%A211%E2%84%83-%E5%8C%97%E5%8C%97%E5%9F%BA%E5%AE%9C%E7%95%99%E6%84%8F%E8%BC%83%E5%A4%A7%E9%9B%A8%E5%8B%A2-101509154.html",
          "appIconUrl": "",
          "sourceUniqueId": "content_yahoo",
          "package": ""
        },
        {
          "text": "赴日暗黑打工被捕 今年暴增10倍",
          "url": "https://tw.news.yahoo.com/%E5%8F%B0%E7%81%A3%E4%BA%BA%E8%AA%A4%E4%BF%A1%E6%9A%97%E9%BB%91%E6%89%93%E5%B7%A5%E5%9C%A8%E6%97%A5%E6%9C%AC%E8%A2%AB%E6%8D%95-%E4%BB%8A%E5%B9%B4%E6%9A%B4%E5%A2%9E10%E5%80%8D%E9%81%9450%E4%BA%BA-042948563.html",
          "h5_url": "https://tw.news.yahoo.com/%E5%8F%B0%E7%81%A3%E4%BA%BA%E8%AA%A4%E4%BF%A1%E6%9A%97%E9%BB%91%E6%89%93%E5%B7%A5%E5%9C%A8%E6%97%A5%E6%9C%AC%E8%A2%AB%E6%8D%95-%E4%BB%8A%E5%B9%B4%E6%9A%B4%E5%A2%9E10%E5%80%8D%E9%81%9450%E4%BA%BA-042948563.html",
          "appIconUrl": "",
          "sourceUniqueId": "content_yahoo",
          "package": ""
        },
        {
          "text": "辯論總結 檢：柯文哲刀叉吃人肉",
          "url": "https://tw.news.yahoo.com/%E4%BA%AC%E8%8F%AF%E5%9F%8E%E6%A1%88%E8%A8%80%E8%A9%9E%E8%BE%AF%E8%AB%96-%E5%85%AC%E8%A8%B4%E6%AA%A2%E5%AF%9F%E5%AE%98%E7%A8%B1%E6%9F%AF%E6%96%87%E5%93%B2%E9%AB%98%E9%9B%85%E3%80%8C%E5%88%80%E5%8F%89%E5%90%83%E4%BA%BA%E8%82%89%E3%80%8D-065343632.html",
          "h5_url": "https://tw.news.yahoo.com/%E4%BA%AC%E8%8F%AF%E5%9F%8E%E6%A1%88%E8%A8%80%E8%A9%9E%E8%BE%AF%E8%AB%96-%E5%85%AC%E8%A8%B4%E6%AA%A2%E5%AF%9F%E5%AE%98%E7%A8%B1%E6%9F%AF%E6%96%87%E5%93%B2%E9%AB%98%E9%9B%85%E3%80%8C%E5%88%80%E5%8F%89%E5%90%83%E4%BA%BA%E8%82%89%E3%80%8D-065343632.html",
          "appIconUrl": "",
          "sourceUniqueId": "content_yahoo",
          "package": ""
        },
        {
          "text": "曾鉛中毒 中市前議長張宏年逝世",
          "url": "https://tw.news.yahoo.com/%E5%89%8D%E5%8F%B0%E4%B8%AD%E5%B8%82%E8%AD%B0%E9%95%B7%E5%BC%B5%E5%AE%8F%E5%B9%B4%E9%81%8E%E4%B8%96%E4%BA%AB%E5%A3%BD73%E6%AD%B2-%E7%94%9F%E5%89%8D%E5%85%A8%E5%AE%B6%E9%89%9B%E4%B8%AD%E6%AF%92%E6%8F%AD%E7%99%BC%E9%BB%91%E5%BF%83%E4%B8%AD%E9%86%AB-071542963.html",
          "h5_url": "https://tw.news.yahoo.com/%E5%89%8D%E5%8F%B0%E4%B8%AD%E5%B8%82%E8%AD%B0%E9%95%B7%E5%BC%B5%E5%AE%8F%E5%B9%B4%E9%81%8E%E4%B8%96%E4%BA%AB%E5%A3%BD73%E6%AD%B2-%E7%94%9F%E5%89%8D%E5%85%A8%E5%AE%B6%E9%89%9B%E4%B8%AD%E6%AF%92%E6%8F%AD%E7%99%BC%E9%BB%91%E5%BF%83%E4%B8%AD%E9%86%AB-071542963.html",
          "appIconUrl": "",
          "sourceUniqueId": "content_yahoo",
          "package": ""
        },
        {
          "text": "搭船去石垣島 單程最低2800元",
          "url": "https://tw.news.yahoo.com/%E5%9F%BA%E9%9A%86%E8%87%B3%E7%9F%B3%E5%9E%A3%E5%B3%B6%E6%B8%A1%E8%BC%AA%E6%8B%9A%E5%B9%B4%E5%BA%95%E9%96%8B%E8%88%AA-7%E8%89%99%E7%AD%89%E6%88%BF%E5%9E%8B-%E7%A5%A8%E5%83%B9%E6%9B%9D%E5%85%89-085247607.html",
          "h5_url": "https://tw.news.yahoo.com/%E5%9F%BA%E9%9A%86%E8%87%B3%E7%9F%B3%E5%9E%A3%E5%B3%B6%E6%B8%A1%E8%BC%AA%E6%8B%9A%E5%B9%B4%E5%BA%95%E9%96%8B%E8%88%AA-7%E8%89%99%E7%AD%89%E6%88%BF%E5%9E%8B-%E7%A5%A8%E5%83%B9%E6%9B%9D%E5%85%89-085247607.html",
          "appIconUrl": "",
          "sourceUniqueId": "content_yahoo",
          "package": ""
        },
        {
          "text": "日圓升至2個月最高 換匯成本增加",
          "url": "https://tw.stock.yahoo.com/news/%E6%97%A5%E5%9C%93%E5%8D%872%E5%80%8B%E6%9C%88%E6%9C%80%E9%AB%98%EF%BC%81%E6%8F%9B10%E8%90%AC%E5%85%83%E5%B0%911%E5%BC%B5%E8%BF%AA%E5%A3%AB%E5%B0%BC%E9%96%80%E7%A5%A8-%E5%B0%88%E5%AE%B6%EF%BC%9A%E6%8F%9B%E5%8C%AF%E6%88%90%E6%9C%AC%E6%81%90%E8%B6%8A%E4%BE%86%E8%B6%8A%E8%B2%B4-072133817.html",
          "h5_url": "https://tw.stock.yahoo.com/news/%E6%97%A5%E5%9C%93%E5%8D%872%E5%80%8B%E6%9C%88%E6%9C%80%E9%AB%98%EF%BC%81%E6%8F%9B10%E8%90%AC%E5%85%83%E5%B0%911%E5%BC%B5%E8%BF%AA%E5%A3%AB%E5%B0%BC%E9%96%80%E7%A5%A8-%E5%B0%88%E5%AE%B6%EF%BC%9A%E6%8F%9B%E5%8C%AF%E6%88%90%E6%9C%AC%E6%81%90%E8%B6%8A%E4%BE%86%E8%B6%8A%E8%B2%B4-072133817.html",
          "appIconUrl": "",
          "sourceUniqueId": "content_yahoo",
          "package": ""
        },
        {
          "text": "「獼猴包尿布」上街 新北警帶走",
          "url": "https://tw.news.yahoo.com/%E6%96%B0%E5%8C%97%E8%A1%97%E9%A0%AD%E9%A9%9A%E8%A6%8B%E5%8C%85%E5%B0%BF%E5%B8%83%E7%8D%BC%E7%8C%B4-%E9%81%95%E6%B3%95%E9%A3%BC%E9%A4%8A%E6%9C%80%E9%AB%98%E5%8F%AF%E7%BD%B0-%E9%80%99%E6%95%B8%E5%AD%97-041619234.html",
          "h5_url": "https://tw.news.yahoo.com/%E6%96%B0%E5%8C%97%E8%A1%97%E9%A0%AD%E9%A9%9A%E8%A6%8B%E5%8C%85%E5%B0%BF%E5%B8%83%E7%8D%BC%E7%8C%B4-%E9%81%95%E6%B3%95%E9%A3%BC%E9%A4%8A%E6%9C%80%E9%AB%98%E5%8F%AF%E7%BD%B0-%E9%80%99%E6%95%B8%E5%AD%97-041619234.html",
          "appIconUrl": "",
          "sourceUniqueId": "content_yahoo",
          "package": ""
        },
        {
          "text": "台電新制 取消84元最低獎勵金",
          "url": "https://tw.news.yahoo.com/%E5%8F%B0%E9%9B%BB%E5%8F%96%E6%B6%88%E7%AF%80%E9%9B%BB%E6%9C%80%E4%BD%8E%E7%8D%8E%E5%8B%B5%E9%87%91-%E8%90%BD%E5%AF%A6%E5%85%AC%E5%B9%B3%E5%8E%9F%E5%89%87-%E4%BC%B0%E8%B2%A1%E5%8B%99%E5%B9%B4%E7%9C%814%E5%84%84%E5%85%83-082322796.html",
          "h5_url": "https://tw.news.yahoo.com/%E5%8F%B0%E9%9B%BB%E5%8F%96%E6%B6%88%E7%AF%80%E9%9B%BB%E6%9C%80%E4%BD%8E%E7%8D%8E%E5%8B%B5%E9%87%91-%E8%90%BD%E5%AF%A6%E5%85%AC%E5%B9%B3%E5%8E%9F%E5%89%87-%E4%BC%B0%E8%B2%A1%E5%8B%99%E5%B9%B4%E7%9C%814%E5%84%84%E5%85%83-082322796.html",
          "appIconUrl": "",
          "sourceUniqueId": "content_yahoo",
          "package": ""
        },
        {
          "text": "憲政危機時刻 王金平：非韓一個人可解決",
          "url": "https://tw.news.yahoo.com/%E6%94%BF%E9%99%A2%E4%B8%8D%E5%89%AF%E7%BD%B2%E8%B2%A1%E5%8A%83%E6%B3%95-%E7%8E%8B%E9%87%91%E5%B9%B3%EF%BC%9A%E7%8F%BE%E5%9C%A8%E6%98%AF%E6%86%B2%E6%94%BF%E5%8D%B1%E6%A9%9F%E6%99%82%E5%88%BB-%E9%9D%9E%E9%9F%93%E5%9C%8B%E7%91%9C%E4%B8%80%E4%BA%BA%E5%8F%AF%E4%BB%A5%E8%A7%A3%E6%B1%BA-044719177.html",
          "h5_url": "https://tw.news.yahoo.com/%E6%94%BF%E9%99%A2%E4%B8%8D%E5%89%AF%E7%BD%B2%E8%B2%A1%E5%8A%83%E6%B3%95-%E7%8E%8B%E9%87%91%E5%B9%B3%EF%BC%9A%E7%8F%BE%E5%9C%A8%E6%98%AF%E6%86%B2%E6%94%BF%E5%8D%B1%E6%A9%9F%E6%99%82%E5%88%BB-%E9%9D%9E%E9%9F%93%E5%9C%8B%E7%91%9C%E4%B8%80%E4%BA%BA%E5%8F%AF%E4%BB%A5%E8%A7%A3%E6%B1%BA-044719177.html",
          "appIconUrl": "",
          "sourceUniqueId": "content_yahoo",
          "package": ""
        }
      ],
      "selectedStatus": false,
      "rank_type": "rank_ahoo"
    },
    {
      "track_id": "hq_google",
      "title": "Google",
      "title_icon_url": "",
      "headImageUrl": "",
      "link_type": "app",
      "data": [
        {
          "text": "財劃法閣揆不副署 賴總統給韓國瑜函文曝光",
          "url": "https://news.google.com/rss/articles/CBMiU0FVX3lxTE1MeUlQR2VIS3ZrOFYzVmJBTEVjemN5XzltalNhZzZRV3FhTlBuVkJYSkdJNWd1WkpwbkI5S1JVRlhRZTRLQkQzSWdBeWlYeUxsZGJB0gFYQVVfeXFMT3lkT1JESFpoN1lmZVR6cW9ieTVxOUYtYkdYdGNsZVhVVkRBaW5SbnNaQm1ja2d2Rm93cEExS2huX3VmRndnTWFSWUE2aUlRRmlpak9BWDB5Uw?oc=5",
          "h5_url": "https://news.google.com/rss/articles/CBMiU0FVX3lxTE1MeUlQR2VIS3ZrOFYzVmJBTEVjemN5XzltalNhZzZRV3FhTlBuVkJYSkdJNWd1WkpwbkI5S1JVRlhRZTRLQkQzSWdBeWlYeUxsZGJB0gFYQVVfeXFMT3lkT1JESFpoN1lmZVR6cW9ieTVxOUYtYkdYdGNsZVhVVkRBaW5SbnNaQm1ja2d2Rm93cEExS2huX3VmRndnTWFSWUE2aUlRRmlpak9BWDB5Uw?oc=5",
          "appIconUrl": "",
          "sourceUniqueId": "content_google",
          "package": ""
        },
        {
          "text": "逆轉！高虹安涉詐領助理費 高院改判貪污無罪、僅登載不實判6月",
          "url": "https://news.google.com/rss/articles/CBMiakFVX3lxTE9KTU9WM25ldmVPQ084YWVpdl9CVEg3X0RRNnFmVE1xSEhBTHZwcWlPUVdPSFpIS2dlUGNrQnN4SktxSlBfRE54OTJtVUNWc3pyX3pHaHNrNnV5NHpRMlltNnJmalBMU0FibkHSAW9BVV95cUxQbEZxcFVWTHQ3YVNvVW9UZTRVR0wtYlpjQlhwSzE4LUJHbUNHOFVMWURaOTdEU1hUZUV2THNiZGdEUUg4WmlFRWZoU2Q2bUFOdHRjbURKS1hpenhid04xdVFZVkVJTEk5Q2pnck5CM2c?oc=5",
          "h5_url": "https://news.google.com/rss/articles/CBMiakFVX3lxTE9KTU9WM25ldmVPQ084YWVpdl9CVEg3X0RRNnFmVE1xSEhBTHZwcWlPUVdPSFpIS2dlUGNrQnN4SktxSlBfRE54OTJtVUNWc3pyX3pHaHNrNnV5NHpRMlltNnJmalBMU0FibkHSAW9BVV95cUxQbEZxcFVWTHQ3YVNvVW9UZTRVR0wtYlpjQlhwSzE4LUJHbUNHOFVMWURaOTdEU1hUZUV2THNiZGdEUUg4WmlFRWZoU2Q2bUFOdHRjbURKS1hpenhid04xdVFZVkVJTEk5Q2pnck5CM2c?oc=5",
          "appIconUrl": "",
          "sourceUniqueId": "content_google",
          "package": ""
        },
        {
          "text": "前台中市議長張宏年過世享壽73歲 生前全家鉛中毒揭發黑心中醫",
          "url": "https://news.google.com/rss/articles/CBMimwNBVV95cUxNQ01NWXRJek1FMHlGeXZLNFdOdVBucW5nRlV2UzhJX2txR25hMFFaakFzaE9BM1BmdjEzcFVCSkk2M1VsQ3NWZnNBYi12YnFlN2tVNHVVTXpNZzVXSjB3dkVuNDlwNW1XT0MtTjY3VVFCdk82OFNTQ24tcVhGTE5CWG9HcnRmY2xDMWpYWnQxTktpdmZaRktmN1JjeEhOMWMtdEVhVURUQW1ZX0g3QUZVLXNmSl9EQVRxTkFQQVIwNzliNGJBOERVUXBwUGtlSGdyTG9BTnRQRHlKWC1BOUlZSk93eHFmUVFxdl9rcW8tazlzWDJTTjRzU0t2OUV4eEtjQldtYmNPNElUdS1qd0FEOWIwSi1ia09HOVEzdndrb1VKaE5YNGxpeHR4SEJkOVdjQjhmdE5zRUlqalNQMEhVaG56SGFua0dBUDF2WHZaa0xJZTBkMkpENkZmaTdScXRVWXRtdzYxeFlINmx3Q3FTUGZOWVZSTnMtUDRtb1JkRFJBZG5MZnlXeXhhYW92U0VvYUJEN3A4bVk2VWc?oc=5",
          "h5_url": "https://news.google.com/rss/articles/CBMimwNBVV95cUxNQ01NWXRJek1FMHlGeXZLNFdOdVBucW5nRlV2UzhJX2txR25hMFFaakFzaE9BM1BmdjEzcFVCSkk2M1VsQ3NWZnNBYi12YnFlN2tVNHVVTXpNZzVXSjB3dkVuNDlwNW1XT0MtTjY3VVFCdk82OFNTQ24tcVhGTE5CWG9HcnRmY2xDMWpYWnQxTktpdmZaRktmN1JjeEhOMWMtdEVhVURUQW1ZX0g3QUZVLXNmSl9EQVRxTkFQQVIwNzliNGJBOERVUXBwUGtlSGdyTG9BTnRQRHlKWC1BOUlZSk93eHFmUVFxdl9rcW8tazlzWDJTTjRzU0t2OUV4eEtjQldtYmNPNElUdS1qd0FEOWIwSi1ia09HOVEzdndrb1VKaE5YNGxpeHR4SEJkOVdjQjhmdE5zRUlqalNQMEhVaG56SGFua0dBUDF2WHZaa0xJZTBkMkpENkZmaTdScXRVWXRtdzYxeFlINmx3Q3FTUGZOWVZSTnMtUDRtb1JkRFJBZG5MZnlXeXhhYW92U0VvYUJEN3A4bVk2VWc?oc=5",
          "appIconUrl": "",
          "sourceUniqueId": "content_google",
          "package": ""
        },
        {
          "text": "香港末代總督：若仍相信中共可改革應警惕黎智英案",
          "url": "https://news.google.com/rss/articles/CBMiXkFVX3lxTE9md2d3TXRtVWZTcnZ6Z3JCUmZXWUZuQzhBeXNFMlpseTJVMHRrR3BZdDVKTDdaZ1hqZWd6WDFQd3c5OXZPRFJtSEFGbnN1THpuUHFFUEdZa0IwWlFKalE?oc=5",
          "h5_url": "https://news.google.com/rss/articles/CBMiXkFVX3lxTE9md2d3TXRtVWZTcnZ6Z3JCUmZXWUZuQzhBeXNFMlpseTJVMHRrR3BZdDVKTDdaZ1hqZWd6WDFQd3c5OXZPRFJtSEFGbnN1THpuUHFFUEdZa0IwWlFKalE?oc=5",
          "appIconUrl": "",
          "sourceUniqueId": "content_google",
          "package": ""
        },
        {
          "text": "俄烏停火談判有進展美方稱烏克蘭可獲類似北約安全保障",
          "url": "https://news.google.com/rss/articles/CBMiX0FVX3lxTE9falJOZGpKOEpLNS1hOV9NdGl6TGhMcml2YzB6Y3ZTNGdPa2NDZFhRZy1UQUplYW9HOVJHMjctZGVNN3RSZzNYNVdnMDB3TGZlazZ6RWZjNVdUYmN4Nl8w?oc=5",
          "h5_url": "https://news.google.com/rss/articles/CBMiX0FVX3lxTE9falJOZGpKOEpLNS1hOV9NdGl6TGhMcml2YzB6Y3ZTNGdPa2NDZFhRZy1UQUplYW9HOVJHMjctZGVNN3RSZzNYNVdnMDB3TGZlazZ6RWZjNVdUYmN4Nl8w?oc=5",
          "appIconUrl": "",
          "sourceUniqueId": "content_google",
          "package": ""
        },
        {
          "text": "台灣人赴日「暗黑打工」詐騙案暴增10倍誤信免費旅遊觸法",
          "url": "https://news.google.com/rss/articles/CBMiX0FVX3lxTE5DQWI5R2FlYzl1dS1WRFdJWjFzNVFJV3AwelgxMjRnclNlREVkXzA1RFd3Vk9CeWMtZGVSaXkwMmVva3o5THdBNWs2X0pEOFdvVDMxdlBrcnUtMW1HS2pz?oc=5",
          "h5_url": "https://news.google.com/rss/articles/CBMiX0FVX3lxTE5DQWI5R2FlYzl1dS1WRFdJWjFzNVFJV3AwelgxMjRnclNlREVkXzA1RFd3Vk9CeWMtZGVSaXkwMmVva3o5THdBNWs2X0pEOFdvVDMxdlBrcnUtMW1HS2pz?oc=5",
          "appIconUrl": "",
          "sourceUniqueId": "content_google",
          "package": ""
        },
        {
          "text": "兩波東北季風影響！今清晨最低溫9.1度 7縣市低溫特報",
          "url": "https://news.google.com/rss/articles/CBMi4AJBVV95cUxNVVdhdGU2QkU3bTNtbXk2ZS1FNTgyYUVURHoyUUZxSDJ5dkUzcU11YVEyRHUzUWFxZWpTYTJxQWRpLVFFSTZvMlJETWVvZXl5NGV1Uzd6NHNpYThRVDdUQlNTWkh0TXFtY2U0TUY5VDlGU2Z3QnZFdEFEM2k0Y1ZCR3J4U1JLOVU1RnhPODBxVW4tRElyNkt1NzlhTHFhSmNvMFRoUDR3Wm9YSDRxcmZ4dFJ1Z29VSmFkaFZ2a1Rwc1pCVHBlbW5EYXRleFFjbU5KS3Z2SjJqc1VSbDdTSXpsRWZsWGllUzlnTE54b3FxZEpNcjNOMGZaMGdIbW1OY1RPR2tnT0NpdW1McHVxRnc4VUdqd0RYM1Q4TlZTMkZPTjJSTVg4V0ljN3JQSlhvZ2pEdDg2UnRwbDdMcnlXR3NzeXd3OFZHOTNYMEhWOTNPY0k4VXJUM0JTem1aazY3ZlVr?oc=5",
          "h5_url": "https://news.google.com/rss/articles/CBMi4AJBVV95cUxNVVdhdGU2QkU3bTNtbXk2ZS1FNTgyYUVURHoyUUZxSDJ5dkUzcU11YVEyRHUzUWFxZWpTYTJxQWRpLVFFSTZvMlJETWVvZXl5NGV1Uzd6NHNpYThRVDdUQlNTWkh0TXFtY2U0TUY5VDlGU2Z3QnZFdEFEM2k0Y1ZCR3J4U1JLOVU1RnhPODBxVW4tRElyNkt1NzlhTHFhSmNvMFRoUDR3Wm9YSDRxcmZ4dFJ1Z29VSmFkaFZ2a1Rwc1pCVHBlbW5EYXRleFFjbU5KS3Z2SjJqc1VSbDdTSXpsRWZsWGllUzlnTE54b3FxZEpNcjNOMGZaMGdIbW1OY1RPR2tnT0NpdW1McHVxRnc4VUdqd0RYM1Q4TlZTMkZPTjJSTVg4V0ljN3JQSlhvZ2pEdDg2UnRwbDdMcnlXR3NzeXd3OFZHOTNYMEhWOTNPY0k4VXJUM0JTem1aazY3ZlVr?oc=5",
          "appIconUrl": "",
          "sourceUniqueId": "content_google",
          "package": ""
        },
        {
          "text": "台灣茶赴法國比賽獲獎 中國大使館叫囂遭噓聲[影]",
          "url": "https://news.google.com/rss/articles/CBMiX0FVX3lxTE5la0FDeGgxVWZFS3RSS3N4MHEyc2d6TTd6TjljRElvYl9NWTc5cEVpV0FZdTB3cnl0QUg3Wm1zb1QxZWd4d2FmNEhzc3pNbi1mSllnV3hLcng1MFNHUlRZ?oc=5",
          "h5_url": "https://news.google.com/rss/articles/CBMiX0FVX3lxTE5la0FDeGgxVWZFS3RSS3N4MHEyc2d6TTd6TjljRElvYl9NWTc5cEVpV0FZdTB3cnl0QUg3Wm1zb1QxZWd4d2FmNEhzc3pNbi1mSllnV3hLcng1MFNHUlRZ?oc=5",
          "appIconUrl": "",
          "sourceUniqueId": "content_google",
          "package": ""
        },
        {
          "text": "檢方論告：京華城案是全國唯一違法量身打造| 法律前線",
          "url": "https://news.google.com/rss/articles/CBMiUEFVX3lxTE13YURlbnRUSWNtbl9NaTBTOVE3OThmLVVJTEJyYzY4TlF2OThNYWI4SUV1UXlkak52Y3QwQktVQ3hOUVRNTW5NdmRPcURLMVpk?oc=5",
          "h5_url": "https://news.google.com/rss/articles/CBMiUEFVX3lxTE13YURlbnRUSWNtbl9NaTBTOVE3OThmLVVJTEJyYzY4TlF2OThNYWI4SUV1UXlkak52Y3QwQktVQ3hOUVRNTW5NdmRPcURLMVpk?oc=5",
          "appIconUrl": "",
          "sourceUniqueId": "content_google",
          "package": ""
        },
        {
          "text": "火藥標案惹議 顧立雄怒了：設立資本額、計較公司名字就能讓他履約？",
          "url": "https://news.google.com/rss/articles/CBMipwNBVV95cUxPTmxrdU45VkRLT1dPaW1aZVI3RmdYRVVqX08xWFc5UlJYUUZtQUNWTmNaUWRZdE5TcU9fMUlRUTE1STRDZWdJNE9sWlR3M3dQSG14NHAtdUdQSDVIRVE5MXFObTZXRjVaeVRvWTVDcmJ1VndlSVk2cnMyUUdoRXN3SVUyTW9pWTQxVWluNnRDRXZGQS05QW9xT0F2QTZpdVhIcFFvZnJpaHR2NzNZRG9ZdngxbmczWEpNLVBTSHp4c2w0YlBHaFJqRko1Z1B0T3l0Y2x0NDJsWmZEQ3hDbld5cVpGVVUyemxSaFVZalFhbU5EV3V5SVR1TW5PZXRTcE5zTGlRNW5Vclp0RDNtVUF6R21jcXpHdG8zMW9fRTdrNjJXalFJNGRSdnBVbFY4SXkyQ1V0Q1ZKS3ZpNnpYLVlzTHAxNXpUVzFqWnNwVEk1S0JabmFPQW1hd1pKc1BCYTBCLU9ITEZ0T3Y3M1VZSDYtb3FnRjAxdmt4RTFTU0k4c3B5cDZ5OXFMYWhLV2pTODlwUUhSdkVtcldTbGgyV09VYjBSclc0VEU?oc=5",
          "h5_url": "https://news.google.com/rss/articles/CBMipwNBVV95cUxPTmxrdU45VkRLT1dPaW1aZVI3RmdYRVVqX08xWFc5UlJYUUZtQUNWTmNaUWRZdE5TcU9fMUlRUTE1STRDZWdJNE9sWlR3M3dQSG14NHAtdUdQSDVIRVE5MXFObTZXRjVaeVRvWTVDcmJ1VndlSVk2cnMyUUdoRXN3SVUyTW9pWTQxVWluNnRDRXZGQS05QW9xT0F2QTZpdVhIcFFvZnJpaHR2NzNZRG9ZdngxbmczWEpNLVBTSHp4c2w0YlBHaFJqRko1Z1B0T3l0Y2x0NDJsWmZEQ3hDbld5cVpGVVUyemxSaFVZalFhbU5EV3V5SVR1TW5PZXRTcE5zTGlRNW5Vclp0RDNtVUF6R21jcXpHdG8zMW9fRTdrNjJXalFJNGRSdnBVbFY4SXkyQ1V0Q1ZKS3ZpNnpYLVlzTHAxNXpUVzFqWnNwVEk1S0JabmFPQW1hd1pKc1BCYTBCLU9ITEZ0T3Y3M1VZSDYtb3FnRjAxdmt4RTFTU0k4c3B5cDZ5OXFMYWhLV2pTODlwUUhSdkVtcldTbGgyV09VYjBSclc0VEU?oc=5",
          "appIconUrl": "",
          "sourceUniqueId": "content_google",
          "package": ""
        },
        {
          "text": "澳洲16死槍擊案凶嫌父出身印度！父子作案前詭赴菲律賓待近1個月",
          "url": "https://news.google.com/rss/articles/CBMiUEFVX3lxTE1KbllrZEFiSUNqeXNwbUw3WE1FUHQtcjg5ZklEWjVWQXNmaVVDSW9FRS05UGY4TTlzUXdGSGxSYTVsOU1uQm5jRnctQ0ppYkRr0gFWQVVfeXFMTnZGckNHcGIxVUVQelZjZlZwUVVaVl9UU3lRYU9abE9DTDVnNTdLWkZLTnFYX3NTVmJxY0FCMDlkaHZtSFk0aEt3UzhrRTBSTGY3c1owd1E?oc=5",
          "h5_url": "https://news.google.com/rss/articles/CBMiUEFVX3lxTE1KbllrZEFiSUNqeXNwbUw3WE1FUHQtcjg5ZklEWjVWQXNmaVVDSW9FRS05UGY4TTlzUXdGSGxSYTVsOU1uQm5jRnctQ0ppYkRr0gFWQVVfeXFMTnZGckNHcGIxVUVQelZjZlZwUVVaVl9UU3lRYU9abE9DTDVnNTdLWkZLTnFYX3NTVmJxY0FCMDlkaHZtSFk0aEt3UzhrRTBSTGY3c1owd1E?oc=5",
          "appIconUrl": "",
          "sourceUniqueId": "content_google",
          "package": ""
        },
        {
          "text": "逃過一劫！外媒：川普關稅出現大漏洞 台灣42％商品沒課稅",
          "url": "https://news.google.com/rss/articles/CBMiX0FVX3lxTE9iTjNVV2JtUzFjS3FxeExhcWtTX0tVdVNuekQwb2VVa1dodjFFV2k5SXgyaWFWLU5QcnlTY1UwR2RRVG9YdDdLSnhYSW5OeUE1ZE1BRDhDaTFhN0hBanRv0gFkQVVfeXFMT0VVUVE4VEVvTTBZb0Nka3BLMDlVamVjUGhCUGFUOVBoUlFMM1pocnFYRzRMN2REUVVCMU54ZHhqN20yZmpMZDc1Q2g0Zk1WczdwV2ZDZFN3dnZ0OXdvNFI4OEs3TQ?oc=5",
          "h5_url": "https://news.google.com/rss/articles/CBMiX0FVX3lxTE9iTjNVV2JtUzFjS3FxeExhcWtTX0tVdVNuekQwb2VVa1dodjFFV2k5SXgyaWFWLU5QcnlTY1UwR2RRVG9YdDdLSnhYSW5OeUE1ZE1BRDhDaTFhN0hBanRv0gFkQVVfeXFMT0VVUVE4VEVvTTBZb0Nka3BLMDlVamVjUGhCUGFUOVBoUlFMM1pocnFYRzRMN2REUVVCMU54ZHhqN20yZmpMZDc1Q2g0Zk1WczdwV2ZDZFN3dnZ0OXdvNFI4OEs3TQ?oc=5",
          "appIconUrl": "",
          "sourceUniqueId": "content_google",
          "package": ""
        },
        {
          "text": "日本青森外海再震！規模5.2、最大震度3 北海道等地明顯搖晃",
          "url": "https://news.google.com/rss/articles/CBMi8AJBVV95cUxNNXpZd1U3eFk2dWh6dlg4X3NRdUlIZnhHWnlQLTRDbHFWMVl6LXdoQlNBcGNQMEE5cThuS1RqaGVqdVZ1bFpyM0hEVVNHY1M5bG80QnA5Tl9TODZ6Tlkxc1lrZVozWWRhZ3JhdWZGMDVYUDJvVGZRR1laX0p4ZDBfc0JmUWt2S3VkQ0tFb1F6eFQyT3h5WVBKZUdHbjNTOWlxUHYyN2F6empCT215eG9XaXFVMEtoNkp4RVU4TEFzT3JzbDFHMF92R21MdnRaVXZGalJQQXFnU1Zzcm1QYUdnRm16TWRGdVJwWnUyOTlnc204aFU1ZE9leWxMZWdLejdWN0xkYjk3bzNpeXdjRVlYeC1TSlhpRHpyMnF2U3R5ZldSZklIUlRJX3Y1N01zaTlXM0FHOUE2cFNvMjNqN1pPc2lFUW5jQmwwVjRCbFBnOFpnSk9nMEU3bjdYRGlPWG9NYkZTUnpwbWtHRV9DOWxObg?oc=5",
          "h5_url": "https://news.google.com/rss/articles/CBMi8AJBVV95cUxNNXpZd1U3eFk2dWh6dlg4X3NRdUlIZnhHWnlQLTRDbHFWMVl6LXdoQlNBcGNQMEE5cThuS1RqaGVqdVZ1bFpyM0hEVVNHY1M5bG80QnA5Tl9TODZ6Tlkxc1lrZVozWWRhZ3JhdWZGMDVYUDJvVGZRR1laX0p4ZDBfc0JmUWt2S3VkQ0tFb1F6eFQyT3h5WVBKZUdHbjNTOWlxUHYyN2F6empCT215eG9XaXFVMEtoNkp4RVU4TEFzT3JzbDFHMF92R21MdnRaVXZGalJQQXFnU1Zzcm1QYUdnRm16TWRGdVJwWnUyOTlnc204aFU1ZE9leWxMZWdLejdWN0xkYjk3bzNpeXdjRVlYeC1TSlhpRHpyMnF2U3R5ZldSZklIUlRJX3Y1N01zaTlXM0FHOUE2cFNvMjNqN1pPc2lFUW5jQmwwVjRCbFBnOFpnSk9nMEU3bjdYRGlPWG9NYkZTUnpwbWtHRV9DOWxObg?oc=5",
          "appIconUrl": "",
          "sourceUniqueId": "content_google",
          "package": ""
        },
        {
          "text": "飯店免費房型升等怎麼拿？前員工揭「最佳入住時間」",
          "url": "https://news.google.com/rss/articles/CBMiX0FVX3lxTE12VnluZGVZTk5RQ0U1bWt1WGw4RTctNHY2d0VoNTNPYTlHbFRRejNkUThmVkRTbEVpNVhZX3VYS2MwcFVzWlJuMml4TUY0Q1lFNGU4NGhMSF9yYklSYk400gFkQVVfeXFMT3RRdWxnZTAzYW9iUDFBLTVJWjhhWXQxdkF2dDliSUlNOTBXaVl5Q3NqNnlScGxOcmRkZWllc3p6TlEyS3p0YXFyVWo1aWRSYWpIcmVnYXlVQ2FLTWk1YUVrYzZ3TA?oc=5",
          "h5_url": "https://news.google.com/rss/articles/CBMiX0FVX3lxTE12VnluZGVZTk5RQ0U1bWt1WGw4RTctNHY2d0VoNTNPYTlHbFRRejNkUThmVkRTbEVpNVhZX3VYS2MwcFVzWlJuMml4TUY0Q1lFNGU4NGhMSF9yYklSYk400gFkQVVfeXFMT3RRdWxnZTAzYW9iUDFBLTVJWjhhWXQxdkF2dDliSUlNOTBXaVl5Q3NqNnlScGxOcmRkZWllc3p6TlEyS3p0YXFyVWo1aWRSYWpIcmVnYXlVQ2FLTWk1YUVrYzZ3TA?oc=5",
          "appIconUrl": "",
          "sourceUniqueId": "content_google",
          "package": ""
        },
        {
          "text": "台股收盤》台積電、指數同步跌破月線 大盤收跌330點",
          "url": "https://news.google.com/rss/articles/CBMiX0FVX3lxTE91RHlVRzlMVEF1NVNfNjZRdlVyZzF4VTZvVmlidzlBQVFyQnZDRU8xa3hVMUZwbXloM0k1WDVOUlhPZWxIYW5VaXlHZ003Z0djeUw2eEVTSTI3RkNmbGJN0gFkQVVfeXFMTXBKckhYdzVXVEV2bTdScXN6Rmw5bGg0TWhuYlg0dE9TMFNLcmhFNjJ5YjBuSkdmaGV0QjBpMTVCTnZkR1ZuVTVSazZqM3NDN1FUWEp4TlRfUEZtWl8wQTdLa25HMg?oc=5",
          "h5_url": "https://news.google.com/rss/articles/CBMiX0FVX3lxTE91RHlVRzlMVEF1NVNfNjZRdlVyZzF4VTZvVmlidzlBQVFyQnZDRU8xa3hVMUZwbXloM0k1WDVOUlhPZWxIYW5VaXlHZ003Z0djeUw2eEVTSTI3RkNmbGJN0gFkQVVfeXFMTXBKckhYdzVXVEV2bTdScXN6Rmw5bGg0TWhuYlg0dE9TMFNLcmhFNjJ5YjBuSkdmaGV0QjBpMTVCTnZkR1ZuVTVSazZqM3NDN1FUWEp4TlRfUEZtWl8wQTdLa25HMg?oc=5",
          "appIconUrl": "",
          "sourceUniqueId": "content_google",
          "package": ""
        }
      ],
      "selectedStatus": false,
      "rank_type": "rank_google"
    }
  ],
  "hash": "c2d15b8822404d2ea10f48b759eadba1",
  "qt": "composite_ad_yahoo_google",
  "message": "success",
  "cost": 18,
  "status": 0
}