{
  "config_id": "R-10",
  "updateIntervalMinutes": {
    "2G": 20,
    "3G": 20,
    "4G": 20,
    "WIFI": 20
  },
  "result": [
    {
      "track_id": "hq_yahoo",
      "title": "Yahoo!",
      "title_icon_url": "",
      "headImageUrl": "",
      "link_type": "app",
      "data": [
        {
          "text": "「天才少女」世運會摘金 擊敗中國選手",
          "url": "https://tw.sports.yahoo.com/news/%E6%88%90%E9%83%BD%E4%B8%96%E9%81%8B-%E5%8F%B0%E7%81%A3-%E4%B8%AD%E8%8F%AF%E9%9A%8A-%E9%81%B8%E6%89%8B-%E5%90%8D%E5%96%AE-%E8%B3%BD%E7%A8%8B-%E7%9B%B4%E6%92%AD-%E8%BD%89%E6%92%AD-%E9%A0%BB%E9%81%93-%E5%A5%AA%E7%89%8C%E5%96%9C%E5%A0%B1-062049215.html",
          "h5_url": "https://tw.sports.yahoo.com/news/%E6%88%90%E9%83%BD%E4%B8%96%E9%81%8B-%E5%8F%B0%E7%81%A3-%E4%B8%AD%E8%8F%AF%E9%9A%8A-%E9%81%B8%E6%89%8B-%E5%90%8D%E5%96%AE-%E8%B3%BD%E7%A8%8B-%E7%9B%B4%E6%92%AD-%E8%BD%89%E6%92%AD-%E9%A0%BB%E9%81%93-%E5%A5%AA%E7%89%8C%E5%96%9C%E5%A0%B1-062049215.html",
          "appIconUrl": "",
          "sourceUniqueId": "content_yahoo",
          "package": ""
        },
        {
          "text": "王毅要求日本將台灣歸還中國 林佳龍駁斥",
          "url": "https://tw.news.yahoo.com/%E7%8E%8B%E6%AF%85%E5%BC%95%E8%BF%B0%E4%BA%8C%E6%88%B0%E6%96%87%E7%8D%BB%E7%A8%B1%E5%8F%B0%E6%87%89%E6%AD%B8%E4%B8%AD%E5%9C%8B-%E6%9E%97%E4%BD%B3%E9%BE%8D%E5%9A%B4%E6%AD%A3%E9%A7%81%E6%96%A5-032140236.html",
          "h5_url": "https://tw.news.yahoo.com/%E7%8E%8B%E6%AF%85%E5%BC%95%E8%BF%B0%E4%BA%8C%E6%88%B0%E6%96%87%E7%8D%BB%E7%A8%B1%E5%8F%B0%E6%87%89%E6%AD%B8%E4%B8%AD%E5%9C%8B-%E6%9E%97%E4%BD%B3%E9%BE%8D%E5%9A%B4%E6%AD%A3%E9%A7%81%E6%96%A5-032140236.html",
          "appIconUrl": "",
          "sourceUniqueId": "content_yahoo",
          "package": ""
        },
        {
          "text": "刺鼻臭煙嚇壞居民 證實氨氣外洩",
          "url": "https://tw.news.yahoo.com/%E5%AE%9C%E8%98%AD%E5%88%BA%E9%BC%BB%E6%B0%A3%E5%91%B3%E7%99%BD%E7%85%99%E9%A9%9A%E5%9A%87%E5%B1%85%E6%B0%91-%E7%BD%AA%E9%AD%81%E7%AB%9F%E6%98%AF%E5%B7%A5%E5%BB%A0-%E9%80%99%E5%80%8B-%E5%A4%96%E6%B4%A9-024202307.html",
          "h5_url": "https://tw.news.yahoo.com/%E5%AE%9C%E8%98%AD%E5%88%BA%E9%BC%BB%E6%B0%A3%E5%91%B3%E7%99%BD%E7%85%99%E9%A9%9A%E5%9A%87%E5%B1%85%E6%B0%91-%E7%BD%AA%E9%AD%81%E7%AB%9F%E6%98%AF%E5%B7%A5%E5%BB%A0-%E9%80%99%E5%80%8B-%E5%A4%96%E6%B4%A9-024202307.html",
          "appIconUrl": "",
          "sourceUniqueId": "content_yahoo",
          "package": ""
        },
        {
          "text": "川普曝習承諾：只要我是總統 不對台動武",
          "url": "https://tw.news.yahoo.com/%E5%B7%9D%E6%99%AE%E6%9B%9D%E7%BF%92%E8%BF%91%E5%B9%B3%E6%89%BF%E8%AB%BE-%E5%8F%AA%E8%A6%81%E6%88%91%E9%82%84%E6%98%AF%E7%B8%BD%E7%B5%B1-%E4%B8%AD%E5%9C%8B%E4%B8%8D%E6%9C%83%E5%B0%8D%E5%8F%B0%E5%8B%95%E6%AD%A6-003200121.html",
          "h5_url": "https://tw.news.yahoo.com/%E5%B7%9D%E6%99%AE%E6%9B%9D%E7%BF%92%E8%BF%91%E5%B9%B3%E6%89%BF%E8%AB%BE-%E5%8F%AA%E8%A6%81%E6%88%91%E9%82%84%E6%98%AF%E7%B8%BD%E7%B5%B1-%E4%B8%AD%E5%9C%8B%E4%B8%8D%E6%9C%83%E5%B0%8D%E5%8F%B0%E5%8B%95%E6%AD%A6-003200121.html",
          "appIconUrl": "",
          "sourceUniqueId": "content_yahoo",
          "package": ""
        },
        {
          "text": "貧富差距再擴大 最新統計公布",
          "url": "https://tw.news.yahoo.com/%E8%B2%A7%E5%AF%8C%E5%B7%AE%E8%B7%9D-%E5%86%8D%E5%BA%A6%E6%93%B4%E5%A4%A7-224550574.html",
          "h5_url": "https://tw.news.yahoo.com/%E8%B2%A7%E5%AF%8C%E5%B7%AE%E8%B7%9D-%E5%86%8D%E5%BA%A6%E6%93%B4%E5%A4%A7-224550574.html",
          "appIconUrl": "",
          "sourceUniqueId": "content_yahoo",
          "package": ""
        },
        {
          "text": "吳淑珍未脫離險境 陳致中揭休克原因",
          "url": "https://tw.news.yahoo.com/%E5%90%B3%E6%B7%91%E7%8F%8D%E4%BC%91%E5%85%8B%E9%80%81%E9%86%AB-%E9%99%B3%E8%87%B4%E4%B8%AD%E8%AD%89%E5%AF%A6-%E5%B0%9A%E6%9C%AA%E8%84%AB%E9%9B%A2%E9%9A%AA%E5%A2%83-%E5%A7%BF%E5%8B%A2%E6%80%A7%E4%BD%8E%E8%A1%80%E5%A3%93%E5%BC%95%E7%99%BC%E4%BC%91%E5%85%8B-014600525.html",
          "h5_url": "https://tw.news.yahoo.com/%E5%90%B3%E6%B7%91%E7%8F%8D%E4%BC%91%E5%85%8B%E9%80%81%E9%86%AB-%E9%99%B3%E8%87%B4%E4%B8%AD%E8%AD%89%E5%AF%A6-%E5%B0%9A%E6%9C%AA%E8%84%AB%E9%9B%A2%E9%9A%AA%E5%A2%83-%E5%A7%BF%E5%8B%A2%E6%80%A7%E4%BD%8E%E8%A1%80%E5%A3%93%E5%BC%95%E7%99%BC%E4%BC%91%E5%85%8B-014600525.html",
          "appIconUrl": "",
          "sourceUniqueId": "content_yahoo",
          "package": ""
        },
        {
          "text": "幼園爆不當對待 北市教育局發聲",
          "url": "https://tw.news.yahoo.com/%E5%8C%97%E5%B8%82%E6%9F%90%E5%B9%BC%E5%85%92%E5%9C%92%E7%88%86%E4%B8%8D%E7%95%B6%E5%B0%8D%E5%BE%85-%E6%95%99%E8%82%B2%E5%B1%80%EF%BC%9A%E5%BE%9E%E9%87%8D%E5%BE%9E%E5%9A%B4%E8%BE%A6%E7%90%86-015759673.html",
          "h5_url": "https://tw.news.yahoo.com/%E5%8C%97%E5%B8%82%E6%9F%90%E5%B9%BC%E5%85%92%E5%9C%92%E7%88%86%E4%B8%8D%E7%95%B6%E5%B0%8D%E5%BE%85-%E6%95%99%E8%82%B2%E5%B1%80%EF%BC%9A%E5%BE%9E%E9%87%8D%E5%BE%9E%E5%9A%B4%E8%BE%A6%E7%90%86-015759673.html",
          "appIconUrl": "",
          "sourceUniqueId": "content_yahoo",
          "package": ""
        },
        {
          "text": "華府告川普接管警局 兩造達協議",
          "url": "https://tw.news.yahoo.com/%E8%8F%AF%E5%BA%9C%E6%AA%A2%E5%AF%9F%E9%95%B7%E5%91%8A%E5%B7%9D%E6%99%AE%E6%94%BF%E5%BA%9C%E6%8E%A5%E7%AE%A1%E8%AD%A6%E5%B1%80-%E5%85%A9%E9%80%A0%E9%81%94%E6%88%90%E5%8D%94%E8%AD%B0-022917207.html",
          "h5_url": "https://tw.news.yahoo.com/%E8%8F%AF%E5%BA%9C%E6%AA%A2%E5%AF%9F%E9%95%B7%E5%91%8A%E5%B7%9D%E6%99%AE%E6%94%BF%E5%BA%9C%E6%8E%A5%E7%AE%A1%E8%AD%A6%E5%B1%80-%E5%85%A9%E9%80%A0%E9%81%94%E6%88%90%E5%8D%94%E8%AD%B0-022917207.html",
          "appIconUrl": "",
          "sourceUniqueId": "content_yahoo",
          "package": ""
        },
        {
          "text": "Meta機器人「引誘」美翁赴約意外喪命",
          "url": "https://tw.news.yahoo.com/meta%E8%81%8A%E5%A4%A9%E6%A9%9F%E5%99%A8%E4%BA%BA%E5%BC%95%E8%AA%98-%E7%BE%8E%E5%9C%8B76%E6%AD%B2%E7%BF%81%E8%B5%B4%E7%B4%84%E6%84%8F%E5%A4%96%E5%96%AA%E5%91%BD-152244576.html",
          "h5_url": "https://tw.news.yahoo.com/meta%E8%81%8A%E5%A4%A9%E6%A9%9F%E5%99%A8%E4%BA%BA%E5%BC%95%E8%AA%98-%E7%BE%8E%E5%9C%8B76%E6%AD%B2%E7%BF%81%E8%B5%B4%E7%B4%84%E6%84%8F%E5%A4%96%E5%96%AA%E5%91%BD-152244576.html",
          "appIconUrl": "",
          "sourceUniqueId": "content_yahoo",
          "package": ""
        },
        {
          "text": "日本旅遊注意 9月起大阪住宿稅調整",
          "url": "https://tw.news.yahoo.com/%E6%97%A5%E6%9C%AC%E6%97%85%E9%81%8A%E6%B3%A8%E6%84%8F-9%E6%9C%88%E8%B5%B7%E5%A4%A7%E9%98%AA%E4%BD%8F%E5%AE%BF%E7%A8%85%E8%AA%BF%E6%95%B4-%E8%A8%82%E9%A3%AF%E5%BA%97%E6%81%90%E5%A2%9E%E9%A1%8D%E5%A4%96%E6%94%AF%E5%87%BA-223315212.html",
          "h5_url": "https://tw.news.yahoo.com/%E6%97%A5%E6%9C%AC%E6%97%85%E9%81%8A%E6%B3%A8%E6%84%8F-9%E6%9C%88%E8%B5%B7%E5%A4%A7%E9%98%AA%E4%BD%8F%E5%AE%BF%E7%A8%85%E8%AA%BF%E6%95%B4-%E8%A8%82%E9%A3%AF%E5%BA%97%E6%81%90%E5%A2%9E%E9%A1%8D%E5%A4%96%E6%94%AF%E5%87%BA-223315212.html",
          "appIconUrl": "",
          "sourceUniqueId": "content_yahoo",
          "package": ""
        },
        {
          "text": "美前官員：川普沒有輸 但普丁明顯贏了",
          "url": "https://tw.news.yahoo.com/%E6%99%AE%E4%B8%81%E6%90%AD%E6%A9%9F%E5%BF%AB%E9%96%83%E5%9B%9E%E4%BF%84%E7%BE%85%E6%96%AF-%E5%B7%9D%E6%99%AE%E5%89%8D%E5%AE%98%E5%93%A1-%E5%B7%9D%E6%99%AE%E6%B2%92%E6%9C%89%E8%BC%B8-%E4%BD%86%E6%99%AE%E4%B8%81%E6%98%8E%E9%A1%AF%E8%B4%8F%E4%BA%86-003700564.html",
          "h5_url": "https://tw.news.yahoo.com/%E6%99%AE%E4%B8%81%E6%90%AD%E6%A9%9F%E5%BF%AB%E9%96%83%E5%9B%9E%E4%BF%84%E7%BE%85%E6%96%AF-%E5%B7%9D%E6%99%AE%E5%89%8D%E5%AE%98%E5%93%A1-%E5%B7%9D%E6%99%AE%E6%B2%92%E6%9C%89%E8%BC%B8-%E4%BD%86%E6%99%AE%E4%B8%81%E6%98%8E%E9%A1%AF%E8%B4%8F%E4%BA%86-003700564.html",
          "appIconUrl": "",
          "sourceUniqueId": "content_yahoo",
          "package": ""
        },
        {
          "text": "攸關烏克蘭和平⋯恐現「雅爾達會議」風險",
          "url": "https://tw.news.yahoo.com/%E7%BE%8E%E4%BF%84%E5%B3%B0%E6%9C%83%E8%AB%87%E7%83%8F%E6%88%B0%E6%9C%AA%E4%BE%86-%E6%81%90%E7%8F%BE%E9%9B%85%E7%88%BE%E9%81%94%E6%9C%83%E8%AD%B02-0%E9%A2%A8%E9%9A%AA-232929990.html",
          "h5_url": "https://tw.news.yahoo.com/%E7%BE%8E%E4%BF%84%E5%B3%B0%E6%9C%83%E8%AB%87%E7%83%8F%E6%88%B0%E6%9C%AA%E4%BE%86-%E6%81%90%E7%8F%BE%E9%9B%85%E7%88%BE%E9%81%94%E6%9C%83%E8%AD%B02-0%E9%A2%A8%E9%9A%AA-232929990.html",
          "appIconUrl": "",
          "sourceUniqueId": "content_yahoo",
          "package": ""
        },
        {
          "text": "外媒分析普丁更想談大國關係「調整世界秩序」",
          "url": "https://tw.news.yahoo.com/%E7%BE%8E%E4%BF%84%E5%B3%B0%E6%9C%83%E7%84%A6%E9%BB%9E%E4%B8%8D%E5%8F%AA%E7%83%8F%E5%85%8B%E8%98%AD-%E5%BE%B7%E5%AA%92-%E8%92%B2%E4%BA%AD%E6%83%B3%E8%AB%87%E5%A4%A7%E5%9C%8B%E9%97%9C%E4%BF%82-233831936.html",
          "h5_url": "https://tw.news.yahoo.com/%E7%BE%8E%E4%BF%84%E5%B3%B0%E6%9C%83%E7%84%A6%E9%BB%9E%E4%B8%8D%E5%8F%AA%E7%83%8F%E5%85%8B%E8%98%AD-%E5%BE%B7%E5%AA%92-%E8%92%B2%E4%BA%AD%E6%83%B3%E8%AB%87%E5%A4%A7%E5%9C%8B%E9%97%9C%E4%BF%82-233831936.html",
          "appIconUrl": "",
          "sourceUniqueId": "content_yahoo",
          "package": ""
        },
        {
          "text": "澤倫斯基未獲邀掀反彈 烏克蘭人強烈抗議",
          "url": "https://tw.news.yahoo.com/%E9%9B%99%E6%99%AE%E6%9C%83%E6%9C%AA%E9%82%80%E6%BE%A4%E5%80%AB%E6%96%AF%E5%9F%BA%E5%BC%95%E5%8F%8D%E5%BD%88-%E7%83%8F%E5%85%8B%E8%98%AD%E4%BA%BA%E8%A2%AB%E9%82%8A%E7%B7%A3%E5%8C%96%E6%89%B9-%E5%96%AA%E6%AC%8A%E8%BE%B1%E5%9C%8B-225804932.html",
          "h5_url": "https://tw.news.yahoo.com/%E9%9B%99%E6%99%AE%E6%9C%83%E6%9C%AA%E9%82%80%E6%BE%A4%E5%80%AB%E6%96%AF%E5%9F%BA%E5%BC%95%E5%8F%8D%E5%BD%88-%E7%83%8F%E5%85%8B%E8%98%AD%E4%BA%BA%E8%A2%AB%E9%82%8A%E7%B7%A3%E5%8C%96%E6%89%B9-%E5%96%AA%E6%AC%8A%E8%BE%B1%E5%9C%8B-225804932.html",
          "appIconUrl": "",
          "sourceUniqueId": "content_yahoo",
          "package": ""
        },
        {
          "text": "本日焦點／痠痛貼布一次貼逾6片 休克送醫",
          "url": "https://tw.news.yahoo.com/%E3%80%90%E6%9C%AC%E6%97%A5%E7%84%A6%E9%BB%9E%E3%80%91%E7%97%A0%E7%97%9B%E8%B2%BC%E5%B8%83%E4%B8%80%E6%AC%A1%E8%B2%BC%E9%80%BE6%E7%89%87-%E8%A7%A3%E9%BB%91%E4%BE%BF%E4%BC%91%E5%85%8B%E9%80%81%E9%86%AB%EF%BC%8F%E9%A3%9B%E4%BB%81%E5%B7%9D%E5%8D%BB%E7%AA%81%E6%94%B9%E9%99%8D%E9%87%91%E6%B5%A6%E8%AE%93%E4%BA%BA%E9%8C%AF%E6%84%95%E2%8B%AF%E4%BA%9E%E8%88%AA%E8%A7%A3%E9%87%8B%EF%BC%8F%E5%BD%AD%E5%95%93%E6%98%8E%EF%B8%B0%E7%9B%A7%E3%80%81%E5%8D%93%E4%BA%A4%E9%8B%92-%E5%83%8F%E5%AA%BD%E5%AA%BD%E7%BD%B5%E5%85%92%E5%AD%90-094603507.html",
          "h5_url": "https://tw.news.yahoo.com/%E3%80%90%E6%9C%AC%E6%97%A5%E7%84%A6%E9%BB%9E%E3%80%91%E7%97%A0%E7%97%9B%E8%B2%BC%E5%B8%83%E4%B8%80%E6%AC%A1%E8%B2%BC%E9%80%BE6%E7%89%87-%E8%A7%A3%E9%BB%91%E4%BE%BF%E4%BC%91%E5%85%8B%E9%80%81%E9%86%AB%EF%BC%8F%E9%A3%9B%E4%BB%81%E5%B7%9D%E5%8D%BB%E7%AA%81%E6%94%B9%E9%99%8D%E9%87%91%E6%B5%A6%E8%AE%93%E4%BA%BA%E9%8C%AF%E6%84%95%E2%8B%AF%E4%BA%9E%E8%88%AA%E8%A7%A3%E9%87%8B%EF%BC%8F%E5%BD%AD%E5%95%93%E6%98%8E%EF%B8%B0%E7%9B%A7%E3%80%81%E5%8D%93%E4%BA%A4%E9%8B%92-%E5%83%8F%E5%AA%BD%E5%AA%BD%E7%BD%B5%E5%85%92%E5%AD%90-094603507.html",
          "appIconUrl": "",
          "sourceUniqueId": "content_yahoo",
          "package": ""
        }
      ],
      "selectedStatus": false,
      "rank_type": "rank_ahoo"
    },
    {
      "track_id": "hq_google",
      "title": "Google",
      "title_icon_url": "",
      "headImageUrl": "",
      "link_type": "app",
      "data": [
        {
          "text": "美前國安顧問看美俄峰會：川普沒輸但蒲亭贏了",
          "url": "https://news.google.com/rss/articles/CBMiX0FVX3lxTE1iS1psZzg2TnhFMS1HOEFCVGtkcEdjZFM1UUtxMDFlYXo1aEZVazByaDA3QlpZMVNMLVVUNlA4bGxvWEJkdWo2TWNac0ZleTMxekg3c2RyRXhFQWt2elBF?oc=5",
          "h5_url": "https://news.google.com/rss/articles/CBMiX0FVX3lxTE1iS1psZzg2TnhFMS1HOEFCVGtkcEdjZFM1UUtxMDFlYXo1aEZVazByaDA3QlpZMVNMLVVUNlA4bGxvWEJkdWo2TWNac0ZleTMxekg3c2RyRXhFQWt2elBF?oc=5",
          "appIconUrl": "",
          "sourceUniqueId": "content_google",
          "package": ""
        },
        {
          "text": "核電1度1元、風電6元 童子賢喊：不會持家就辭職",
          "url": "https://news.google.com/rss/articles/CBMiuwJBVV95cUxOS2Q3cEt2dm4xYlVNN0JUemphVVRqeG5XcGp2aGVFdUw0c3RMbVhyc3o5clRGTm9sWU5zYlpsM0lRMzZCYVNHMGVyaFhROXN2QnFnSUFVZmJYRHZUTEVjZmljY1RPaXZBLW1uQnpuYVVBY2pELWE2aHRYZ3ZvS2hhaHVscXdpQzBPd212clc2ampQdnJmTVd2UFU5ako4b2JLTXY0Nlk0V1hVYzZ6cGJGYk03TE5idW95REZfcGtVb0hqTTlSM2ZFSFNnU3JpbFFIbWJ6M05LNzRJcS13NVBUcDFWZktwMjY5NHBneTRKbmhvMnpvaGExQjdraHA0RTRsR2puZEJHQlBiYWxzWlA5ZFduOF9fWERxb3pDemo1aG0yNU8teUJMa3hBUndsN3V6bFNrS3VEV0EwTm8?oc=5",
          "h5_url": "https://news.google.com/rss/articles/CBMiuwJBVV95cUxOS2Q3cEt2dm4xYlVNN0JUemphVVRqeG5XcGp2aGVFdUw0c3RMbVhyc3o5clRGTm9sWU5zYlpsM0lRMzZCYVNHMGVyaFhROXN2QnFnSUFVZmJYRHZUTEVjZmljY1RPaXZBLW1uQnpuYVVBY2pELWE2aHRYZ3ZvS2hhaHVscXdpQzBPd212clc2ampQdnJmTVd2UFU5ako4b2JLTXY0Nlk0V1hVYzZ6cGJGYk03TE5idW95REZfcGtVb0hqTTlSM2ZFSFNnU3JpbFFIbWJ6M05LNzRJcS13NVBUcDFWZktwMjY5NHBneTRKbmhvMnpvaGExQjdraHA0RTRsR2puZEJHQlBiYWxzWlA5ZFduOF9fWERxb3pDemo1aG0yNU8teUJMa3hBUndsN3V6bFNrS3VEV0EwTm8?oc=5",
          "appIconUrl": "",
          "sourceUniqueId": "content_google",
          "package": ""
        },
        {
          "text": "中國國台辦批賴清德終戰說 陸委會嗆可笑",
          "url": "https://news.google.com/rss/articles/CBMiakFVX3lxTE03YzJJWHJobEFvcEpibXVlNUlFQWNWM1BZbl9KVlNvMGtZaHgwV1pUQmNJZTBDNnAtQUFkN3pQN1JMTjN6Qk5zWEJfNDNHRmtaaVJzWmpDaVdfbkpmQ2w3QW9NYXBaVUIxMlHSAW9BVV95cUxQOHZrYk5xT3d0OVA0bFlzNzV3NU81dXZsWjVZZmdpX281TGxPVVNrQXZHa0xYQzZHOUNJa3FtUGhtcnRmOVB2TnI5NHRRX1c3WFZOYm1XRU9lMmIyTjhSSS14UldWMWd5ai1yRmtwYm8?oc=5",
          "h5_url": "https://news.google.com/rss/articles/CBMiakFVX3lxTE03YzJJWHJobEFvcEpibXVlNUlFQWNWM1BZbl9KVlNvMGtZaHgwV1pUQmNJZTBDNnAtQUFkN3pQN1JMTjN6Qk5zWEJfNDNHRmtaaVJzWmpDaVdfbkpmQ2w3QW9NYXBaVUIxMlHSAW9BVV95cUxQOHZrYk5xT3d0OVA0bFlzNzV3NU81dXZsWjVZZmdpX281TGxPVVNrQXZHa0xYQzZHOUNJa3FtUGhtcnRmOVB2TnI5NHRRX1c3WFZOYm1XRU9lMmIyTjhSSS14UldWMWd5ai1yRmtwYm8?oc=5",
          "appIconUrl": "",
          "sourceUniqueId": "content_google",
          "package": ""
        },
        {
          "text": "快訊／吳淑珍送醫一度命危！最新病況曝光　陳水扁急赴醫院",
          "url": "https://news.google.com/rss/articles/CBMiXkFVX3lxTE45SUgxY0thalZGVEdWd3VUNHZHdWE3WXBNQVNkUjBtVGtES29ncnhFMjN2bVBobnlHUWE1YjlJd3lEbUZwQ19iMnR1aWhZUGlneGRLcTNVc1d1dXh4Q1HSAWhBVV95cUxPSlBkQXQ1bFBOVlZEUVpJbm1rQldveHl4a1o4eEEyeDZTdldPSVJRcEE1VF9ia1RKYWlBbXI2UDZfZDlXd1dmX3paLXRjMTkzUUNUcjhMRFBCMHpSUzhTbnloU3BJcEVxQw?oc=5",
          "h5_url": "https://news.google.com/rss/articles/CBMiXkFVX3lxTE45SUgxY0thalZGVEdWd3VUNHZHdWE3WXBNQVNkUjBtVGtES29ncnhFMjN2bVBobnlHUWE1YjlJd3lEbUZwQ19iMnR1aWhZUGlneGRLcTNVc1d1dXh4Q1HSAWhBVV95cUxPSlBkQXQ1bFBOVlZEUVpJbm1rQldveHl4a1o4eEEyeDZTdldPSVJRcEE1VF9ia1RKYWlBbXI2UDZfZDlXd1dmX3paLXRjMTkzUUNUcjhMRFBCMHpSUzhTbnloU3BJcEVxQw?oc=5",
          "appIconUrl": "",
          "sourceUniqueId": "content_google",
          "package": ""
        },
        {
          "text": "普發一萬盼立法院盡速通過修正草案 卓榮泰︰行政院將用最快速度編特別預算",
          "url": "https://news.google.com/rss/articles/CBMi7ANBVV95cUxNajJsWi13eDBRVXJ5dTVDUS1ReTNwMGhtenVQYWU1dmZYOXRjQXlUek1RMXgycFRaWmJlMmhDZ0UwSXFJZ2Vodm12ZmxoOTROZmFBUmE0WldadVFQSlcyOUhZZnJKbXF3QmNUM29QbTlySGdXM0owWl9mMU0yRm5lYmpXbWFFeGc4TG5JUmU2bHQ4cW1KMzNUaXdMUHZBSEV6Z1pZamJLY21FTFJKNDhFbXFfbHdQcDZyMXBXRzlDZC11WWxHWkRiZDl2dERVXzNIMlNkSXk2S0ZJNUwwUG9QeHhfMlQ5WTJTM1lyWWtVLUd4aTZiNDZyVXpUNEJpdGJ6bVJvOElma3NhZWxfeHdkWC1sRU5xRlhhWUEwWmRudjRaOEFLbVRPYTVZaFpzM2d0djYwSW93R0pXVGVRNEgxanhYckYwdGE2aUkyTTBWTG95VVRUdEFqaTB1UTQ1ZURMUUdkTjhfTFBNQjRpYjBaSWtYYnlySjZtcnRtNGdxWXljM2FhN0x1ZlB6cWV4d2tlT3p3bjVhWU5ocWdReWkwVmNhTlN6alJFS2VIa19PeDdfdUpPZDJaSk9aLVRmNUNPbVVDZWhmc21oYjgtUmRZUE5nSk9VaUgtQlowQmE3eU1nSXp4djNYLXNUc3E?oc=5",
          "h5_url": "https://news.google.com/rss/articles/CBMi7ANBVV95cUxNajJsWi13eDBRVXJ5dTVDUS1ReTNwMGhtenVQYWU1dmZYOXRjQXlUek1RMXgycFRaWmJlMmhDZ0UwSXFJZ2Vodm12ZmxoOTROZmFBUmE0WldadVFQSlcyOUhZZnJKbXF3QmNUM29QbTlySGdXM0owWl9mMU0yRm5lYmpXbWFFeGc4TG5JUmU2bHQ4cW1KMzNUaXdMUHZBSEV6Z1pZamJLY21FTFJKNDhFbXFfbHdQcDZyMXBXRzlDZC11WWxHWkRiZDl2dERVXzNIMlNkSXk2S0ZJNUwwUG9QeHhfMlQ5WTJTM1lyWWtVLUd4aTZiNDZyVXpUNEJpdGJ6bVJvOElma3NhZWxfeHdkWC1sRU5xRlhhWUEwWmRudjRaOEFLbVRPYTVZaFpzM2d0djYwSW93R0pXVGVRNEgxanhYckYwdGE2aUkyTTBWTG95VVRUdEFqaTB1UTQ1ZURMUUdkTjhfTFBNQjRpYjBaSWtYYnlySjZtcnRtNGdxWXljM2FhN0x1ZlB6cWV4d2tlT3p3bjVhWU5ocWdReWkwVmNhTlN6alJFS2VIa19PeDdfdUpPZDJaSk9aLVRmNUNPbVVDZWhmc21oYjgtUmRZUE5nSk9VaUgtQlowQmE3eU1nSXp4djNYLXNUc3E?oc=5",
          "appIconUrl": "",
          "sourceUniqueId": "content_google",
          "package": ""
        },
        {
          "text": "2男北海道登山遇襲！1人慘遭野生熊當場拖走 封山搜索仍下落不明",
          "url": "https://news.google.com/rss/articles/CBMinANBVV95cUxONEtIeVN6bTJVTThsWHBTZmp3UVJfckFNRDBuNFdKR3RicGRpLWhPXzF2aDRuTVAzU0w3a2ZvWDVwbTEzOXlxbFkwOUdCOVhPYUljTzVaYmFuOUItMDgxZzl1QVRxTWU2WTByUlJHNks5Y095UlFjWGtWMmcwcjktTkNhWGdPcERxQ0N0T0V5aWZlYmhxVHB0Qk5wQUZRamQtZFZ1MkJnTVZIUHItMDdJNEJ6REZIRmppbjFFV1JMekJxSnJIYldvWFZQekhseTE3ZmZXdVpwYlgyS2QyWTZEbzBIaFJaZDNEUVBvaUpaQ082eGw4VG0zQkZfM25fNXE2eEdHQVJBVUJRZVpXQmtOUzhkUkV4NWdWTEpUYUVMdGxIbmI1aXdNLUVuQkd1N3BNWGRWbXhiOFA4ODcwanhOcmhoMGVDZ2hHcGZtb3dfNUtJdFVrdl9QWDlSdGRkWGFWYkF0NTB0TmRrMmpQZ1NtT1lwTmh3U1RLemlrV3ZQRVFYdUVDY1I4bjFQVS1CS3paX2VrWTRiYjJPTU9y?oc=5",
          "h5_url": "https://news.google.com/rss/articles/CBMinANBVV95cUxONEtIeVN6bTJVTThsWHBTZmp3UVJfckFNRDBuNFdKR3RicGRpLWhPXzF2aDRuTVAzU0w3a2ZvWDVwbTEzOXlxbFkwOUdCOVhPYUljTzVaYmFuOUItMDgxZzl1QVRxTWU2WTByUlJHNks5Y095UlFjWGtWMmcwcjktTkNhWGdPcERxQ0N0T0V5aWZlYmhxVHB0Qk5wQUZRamQtZFZ1MkJnTVZIUHItMDdJNEJ6REZIRmppbjFFV1JMekJxSnJIYldvWFZQekhseTE3ZmZXdVpwYlgyS2QyWTZEbzBIaFJaZDNEUVBvaUpaQ082eGw4VG0zQkZfM25fNXE2eEdHQVJBVUJRZVpXQmtOUzhkUkV4NWdWTEpUYUVMdGxIbmI1aXdNLUVuQkd1N3BNWGRWbXhiOFA4ODcwanhOcmhoMGVDZ2hHcGZtb3dfNUtJdFVrdl9QWDlSdGRkWGFWYkF0NTB0TmRrMmpQZ1NtT1lwTmh3U1RLemlrV3ZQRVFYdUVDY1I4bjFQVS1CS3paX2VrWTRiYjJPTU9y?oc=5",
          "appIconUrl": "",
          "sourceUniqueId": "content_google",
          "package": ""
        },
        {
          "text": "今明注意防曬、防中暑 氣象專家：兩熱帶擾動醞釀中",
          "url": "https://news.google.com/rss/articles/CBMi6AJBVV95cUxPR01FQmd2b2tkZnVaSU1XV3RmWUpIbmtyLVRXUmozd19lWHVvX05XUWVUNDVMS0xHLURVODd0bGZIcTh6MEN0ZUtPX2NDVmpYMVJXNjA0UkpiaVQ4d2d2YWxQWjJvUmRvMjRaSUg0ajk0VHMwY0NBSUVvR2lTcDRNUVRCcXNEcUJLTGRCRWVCcnlpMjNIRkZVT1JOVDg2RDVmSElYUVc4SV9fVkNlSzBGaGprcVc0Um5VTTFTVzVJNG44LUxwdkFOT2dvNEpfbkVjNnpwVEpsYVhFeThOYlM4RzJudG40SnlRVGY0czdfMmZ2X2d0Y2prZDM0MmQ4eEVQOV80ZUVhUlV2aUtuMmlQeklaR2ZNZU9FRkhXM21nVmtBZ0VMTVBSRTJrX1RKa01FRnQtTkJRQTRsS2hBZGdLcXJYQUdMRUo0OEYtQ0FFY2J2YTVMREQzcFhxYTJyTG5nUU9lNGVXMXU?oc=5",
          "h5_url": "https://news.google.com/rss/articles/CBMi6AJBVV95cUxPR01FQmd2b2tkZnVaSU1XV3RmWUpIbmtyLVRXUmozd19lWHVvX05XUWVUNDVMS0xHLURVODd0bGZIcTh6MEN0ZUtPX2NDVmpYMVJXNjA0UkpiaVQ4d2d2YWxQWjJvUmRvMjRaSUg0ajk0VHMwY0NBSUVvR2lTcDRNUVRCcXNEcUJLTGRCRWVCcnlpMjNIRkZVT1JOVDg2RDVmSElYUVc4SV9fVkNlSzBGaGprcVc0Um5VTTFTVzVJNG44LUxwdkFOT2dvNEpfbkVjNnpwVEpsYVhFeThOYlM4RzJudG40SnlRVGY0czdfMmZ2X2d0Y2prZDM0MmQ4eEVQOV80ZUVhUlV2aUtuMmlQeklaR2ZNZU9FRkhXM21nVmtBZ0VMTVBSRTJrX1RKa01FRnQtTkJRQTRsS2hBZGdLcXJYQUdMRUo0OEYtQ0FFY2J2YTVMREQzcFhxYTJyTG5nUU9lNGVXMXU?oc=5",
          "appIconUrl": "",
          "sourceUniqueId": "content_google",
          "package": ""
        },
        {
          "text": "侵門踏戶？跑到台中法院開庭的中國籍律師 被起底是共產黨幹部",
          "url": "https://news.google.com/rss/articles/CBMiakFVX3lxTE1jX2dka09tMFVNM1pmZnhJNG1IYWZKOVRVX09pSDlrVjliY2JHeWdWMThaRW92WF9fYmx1SEplWENJTnVGVTJlb0tPSU5PSTR1TkczZi1ZVXZoeWN3YmlBQVJWYmxtaFZ6X1HSAW9BVV95cUxQekc0Zk5JRHhkRkNDZ2RKMG93S2RydWtoMGN5NzdVQlpRVmpJMVNLaXRheG9kLVcyckRlcDhXV1R4YnBKY3Jtb0gtX0RNbGlfMG5YT2FtS0Q5RFdKUkstUjVjRnBHaGpxVnVXckRqcjQ?oc=5",
          "h5_url": "https://news.google.com/rss/articles/CBMiakFVX3lxTE1jX2dka09tMFVNM1pmZnhJNG1IYWZKOVRVX09pSDlrVjliY2JHeWdWMThaRW92WF9fYmx1SEplWENJTnVGVTJlb0tPSU5PSTR1TkczZi1ZVXZoeWN3YmlBQVJWYmxtaFZ6X1HSAW9BVV95cUxQekc0Zk5JRHhkRkNDZ2RKMG93S2RydWtoMGN5NzdVQlpRVmpJMVNLaXRheG9kLVcyckRlcDhXV1R4YnBKY3Jtb0gtX0RNbGlfMG5YT2FtS0Q5RFdKUkstUjVjRnBHaGpxVnVXckRqcjQ?oc=5",
          "appIconUrl": "",
          "sourceUniqueId": "content_google",
          "package": ""
        },
        {
          "text": "首個沒被擊敗的颱風　楊柳「飆速對決台灣」影像曝！神閃避最高山",
          "url": "https://news.google.com/rss/articles/CBMiXkFVX3lxTFAwNFNMR3A4NnY2dnpfVmRhaTQxSW5xaWZlQXZobGdvNF93eTlueXY2RjR1NnJOeGUzZXY2aTRaY2FkeVVuYkgxYTUzVElTaGxaT2V4eTlfRWtZdXZsWkHSAWhBVV95cUxQUnVmSmZ6WjNnUmVvbExfaW90bkx2X2NWTnBNa3JtVWR4SEFxR0tBRGZFTE1GR21NRXJmMjJ1T1hrT1BGcHFka09mZjBvNG04RlR6TTZqcjVJZGdheHMzZGVZVEFKcWJ1YQ?oc=5",
          "h5_url": "https://news.google.com/rss/articles/CBMiXkFVX3lxTFAwNFNMR3A4NnY2dnpfVmRhaTQxSW5xaWZlQXZobGdvNF93eTlueXY2RjR1NnJOeGUzZXY2aTRaY2FkeVVuYkgxYTUzVElTaGxaT2V4eTlfRWtZdXZsWkHSAWhBVV95cUxQUnVmSmZ6WjNnUmVvbExfaW90bkx2X2NWTnBNa3JtVWR4SEFxR0tBRGZFTE1GR21NRXJmMjJ1T1hrT1BGcHFka09mZjBvNG04RlR6TTZqcjVJZGdheHMzZGVZVEFKcWJ1YQ?oc=5",
          "appIconUrl": "",
          "sourceUniqueId": "content_google",
          "package": ""
        },
        {
          "text": "員工秒變臉！館長訪騰訊誇「支付寶領先全球」　急鞠躬道歉險下跪",
          "url": "https://news.google.com/rss/articles/CBMiTEFVX3lxTE1GNXMtMUNvQ1ZXdjU0VWpkQ25keng1emhLbE5ELXFNLXdJRWtxZkRyd1BSa05IUnZGdlltV0NjVlVBVWNnQUIxancxdDDSAVJBVV95cUxQdzk5aC0wLW9GQmQ5c29HY2lvRDAzVWVnT1lOUVYwb0dYRWNIdkR4cEdxbkFaUlo3LS03ckRDOHpsRlhZMTVMQmtPMDhzTTM0Mk9n?oc=5",
          "h5_url": "https://news.google.com/rss/articles/CBMiTEFVX3lxTE1GNXMtMUNvQ1ZXdjU0VWpkQ25keng1emhLbE5ELXFNLXdJRWtxZkRyd1BSa05IUnZGdlltV0NjVlVBVWNnQUIxancxdDDSAVJBVV95cUxQdzk5aC0wLW9GQmQ5c29HY2lvRDAzVWVnT1lOUVYwb0dYRWNIdkR4cEdxbkFaUlo3LS03ckRDOHpsRlhZMTVMQmtPMDhzTTM0Mk9n?oc=5",
          "appIconUrl": "",
          "sourceUniqueId": "content_google",
          "package": ""
        },
        {
          "text": "川普想拿和平獎 希拉蕊：若他結束烏克蘭戰爭 我會提名他",
          "url": "https://news.google.com/rss/articles/CBMiZkFVX3lxTE9IbV9DLTFDeWMwS2paaVVGOVgzRWZTYVhyNnJrTUVrZG1DWU50RjF2MWdaejJMXzlxekhmWXBKVWlzQVJ4OHZlV242Y3BVOEV1M3BlUkF5NW8yN3FHZzl4Ulk2NTctQdIBa0FVX3lxTE9hTDlXRFBIdjVXZEQyMWlYdDduY09yaHJHMnpDTXgyaFBkaDFvT2pYT1pxZURBMTA5eHg2UFJSVVNrR28wS3hCWlRHdGQycmI4VUVua29WbVAxWjFjTDRwNVJFNno4Y2d6OHZV?oc=5",
          "h5_url": "https://news.google.com/rss/articles/CBMiZkFVX3lxTE9IbV9DLTFDeWMwS2paaVVGOVgzRWZTYVhyNnJrTUVrZG1DWU50RjF2MWdaejJMXzlxekhmWXBKVWlzQVJ4OHZlV242Y3BVOEV1M3BlUkF5NW8yN3FHZzl4Ulk2NTctQdIBa0FVX3lxTE9hTDlXRFBIdjVXZEQyMWlYdDduY09yaHJHMnpDTXgyaFBkaDFvT2pYT1pxZURBMTA5eHg2UFJSVVNrR28wS3hCWlRHdGQycmI4VUVua29WbVAxWjFjTDRwNVJFNno4Y2d6OHZV?oc=5",
          "appIconUrl": "",
          "sourceUniqueId": "content_google",
          "package": ""
        },
        {
          "text": "白宮秘密清單曝光！533家企業按照對川普忠誠度排名惹議",
          "url": "https://news.google.com/rss/articles/CBMiUEFVX3lxTE1CRHFtTHhnNDFjMDdDOG5TZTZwaGt2NTJqUkZuYTNqWmtnWFBNMFhJWDFQSHY5bGNDMXRqN1hkaWctWUd4YVJaOHI4Z1VDZUh50gFWQVVfeXFMT0p2ZWhtN3llS3Fad1hjcnRiY20wVzM5dFA5aGFFVEw5bkhFNWU3Y2p5RnQwSlM4SGlWRVMzV244YWV3c3F3S1NJWkprVG9heWJHTXFiMEE?oc=5",
          "h5_url": "https://news.google.com/rss/articles/CBMiUEFVX3lxTE1CRHFtTHhnNDFjMDdDOG5TZTZwaGt2NTJqUkZuYTNqWmtnWFBNMFhJWDFQSHY5bGNDMXRqN1hkaWctWUd4YVJaOHI4Z1VDZUh50gFWQVVfeXFMT0p2ZWhtN3llS3Fad1hjcnRiY20wVzM5dFA5aGFFVEw5bkhFNWU3Y2p5RnQwSlM4SGlWRVMzV244YWV3c3F3S1NJWkprVG9heWJHTXFiMEE?oc=5",
          "appIconUrl": "",
          "sourceUniqueId": "content_google",
          "package": ""
        },
        {
          "text": "中國經濟低迷躺平文化升級 20億次標籤「老鼠人」",
          "url": "https://news.google.com/rss/articles/CBMiZkFVX3lxTFBVYUdnWlJ2NGZnVTNjSmZPYzFTN19qZ0QxNHh2SDktb3k4eWtma2h4QXNaaHpnRUtxelN3UlU4WlRPS2NQa2x2OHlFd2Q5ZEVFbHdIdDI5ZkEtdXhWWlFiNlBlODBNQdIBa0FVX3lxTE8zVDRDdFhMWkxiRVZPbTFDRTJXSTE3TF9xbHc1WnpOSDRaYW84OEs2Z3d5RWpjOVlnLUZkY0xTbnZ4a2pCVUtRV19VOHh2enF2WkptTkcycm1BdjVXM0NPQ1hDZjdNUE1PMVU0?oc=5",
          "h5_url": "https://news.google.com/rss/articles/CBMiZkFVX3lxTFBVYUdnWlJ2NGZnVTNjSmZPYzFTN19qZ0QxNHh2SDktb3k4eWtma2h4QXNaaHpnRUtxelN3UlU4WlRPS2NQa2x2OHlFd2Q5ZEVFbHdIdDI5ZkEtdXhWWlFiNlBlODBNQdIBa0FVX3lxTE8zVDRDdFhMWkxiRVZPbTFDRTJXSTE3TF9xbHc1WnpOSDRaYW84OEs2Z3d5RWpjOVlnLUZkY0xTbnZ4a2pCVUtRV19VOHh2enF2WkptTkcycm1BdjVXM0NPQ1hDZjdNUE1PMVU0?oc=5",
          "appIconUrl": "",
          "sourceUniqueId": "content_google",
          "package": ""
        },
        {
          "text": "小粉紅冒充日本人怒罵日對戰爭反省不深刻 矢板明夫：可能是認知作戰",
          "url": "https://news.google.com/rss/articles/CBMiakFVX3lxTE9CUl9LSW01N2pYd2pNWE1nX3FqVmpZY1ZvOVp2R2wtcmhwRDhfLXRnSVFvRFpaaU52ejZXcURDRnh0RlVyYy0zdVd5dExtWVYta18tcjBEdXI5SzZ4bFVwZk8tbG1hUlJFMWfSAW9BVV95cUxOaXh1dDB4T0ZkMkJwRUNOZU1xNzF0Y1ZueHhDbHdtdEhqYVdQRWdYcjd3M3FJRHUzZVJTX3psRFdhWXZ5ZEpUWWRnVUVfZ3VWVU9RZjFKWkFXZUJiZlktajVjNzBhMUNrSHNiNFd5bGM?oc=5",
          "h5_url": "https://news.google.com/rss/articles/CBMiakFVX3lxTE9CUl9LSW01N2pYd2pNWE1nX3FqVmpZY1ZvOVp2R2wtcmhwRDhfLXRnSVFvRFpaaU52ejZXcURDRnh0RlVyYy0zdVd5dExtWVYta18tcjBEdXI5SzZ4bFVwZk8tbG1hUlJFMWfSAW9BVV95cUxOaXh1dDB4T0ZkMkJwRUNOZU1xNzF0Y1ZueHhDbHdtdEhqYVdQRWdYcjd3M3FJRHUzZVJTX3psRFdhWXZ5ZEpUWWRnVUVfZ3VWVU9RZjFKWkFXZUJiZlktajVjNzBhMUNrSHNiNFd5bGM?oc=5",
          "appIconUrl": "",
          "sourceUniqueId": "content_google",
          "package": ""
        },
        {
          "text": "台灣AI供應鏈恐挨100%重稅！川普揮半導體關稅大刀...聯電、世界先進都被點名",
          "url": "https://news.google.com/rss/articles/CBMiwwNBVV95cUxNYWNGbnY3d3lqZUtVdUh2NURpa2JzaHVZYm9TVzBaMTNBSmYxZG5SaTZGTWVEdXpPekFlLVpmc2p2RTR6Q1B5M2RQbThzTTQ0VjN5TkN2YVlqWThZQ3VLX3B0U0k3dDJzTHg0WE1Rb0pKV2prQU5GNzlQWUpEaXJZemZ0MGZncHNuLUFNSERpVmt4TmpOUXRTWmVsTjZjeW1NSlUycWw1TTZvVmhwMjVnUGI5SmJEUV90RzdLcFZmdHc0RmQtNTVwTFRuWGVSZDdvU0hrX1QyTldqM0VpUGZBaUVWaExMZEhoelNmZm5MRGppeGJKSkM2dGVNU0c2WXFqMXdZX0k3R0o5bDIydDBnQ0Y2WUd4RUctRExZUm03YVBtNXo0TzB2S1AzRmVFODdoV25ucWVaWW0xZE9kZVpTc0F1Y2FDVV9jVTNyNTl6MUVtblJ6NzZEZ2NIVW4yb1NWSExTa3I1bnVnQjlIQ3NWNWhwOTZleDlNZGp1YmMtRXVwSndDUTNGS1E3Tk9xRk5KbnRTS2lYNkJUdGdJblZRX1FMd1lxazZ2ajBsT1RsRnJBcXVLai1NRm9TQ0Iyb1FFS3lJ?oc=5",
          "h5_url": "https://news.google.com/rss/articles/CBMiwwNBVV95cUxNYWNGbnY3d3lqZUtVdUh2NURpa2JzaHVZYm9TVzBaMTNBSmYxZG5SaTZGTWVEdXpPekFlLVpmc2p2RTR6Q1B5M2RQbThzTTQ0VjN5TkN2YVlqWThZQ3VLX3B0U0k3dDJzTHg0WE1Rb0pKV2prQU5GNzlQWUpEaXJZemZ0MGZncHNuLUFNSERpVmt4TmpOUXRTWmVsTjZjeW1NSlUycWw1TTZvVmhwMjVnUGI5SmJEUV90RzdLcFZmdHc0RmQtNTVwTFRuWGVSZDdvU0hrX1QyTldqM0VpUGZBaUVWaExMZEhoelNmZm5MRGppeGJKSkM2dGVNU0c2WXFqMXdZX0k3R0o5bDIydDBnQ0Y2WUd4RUctRExZUm03YVBtNXo0TzB2S1AzRmVFODdoV25ucWVaWW0xZE9kZVpTc0F1Y2FDVV9jVTNyNTl6MUVtblJ6NzZEZ2NIVW4yb1NWSExTa3I1bnVnQjlIQ3NWNWhwOTZleDlNZGp1YmMtRXVwSndDUTNGS1E3Tk9xRk5KbnRTS2lYNkJUdGdJblZRX1FMd1lxazZ2ajBsT1RsRnJBcXVLai1NRm9TQ0Iyb1FFS3lJ?oc=5",
          "appIconUrl": "",
          "sourceUniqueId": "content_google",
          "package": ""
        }
      ],
      "selectedStatus": false,
      "rank_type": "rank_google"
    }
  ],
  "hash": "c2d15b8822404d2ea10f48b759eadba1",
  "qt": "composite_ad_yahoo_google",
  "message": "success",
  "cost": 14,
  "status": 0
}