{
  "config_id": "R-10",
  "updateIntervalMinutes": {
    "2G": 20,
    "3G": 20,
    "4G": 20,
    "WIFI": 20
  },
  "result": [
    {
      "track_id": "hq_yahoo",
      "title": "Yahoo!",
      "title_icon_url": "",
      "headImageUrl": "",
      "link_type": "app",
      "data": [
        {
          "text": "2026租金補貼懶人包",
          "url": "https://tw.news.yahoo.com/share/b514a5f9-7fa6-40ce-a78e-c93bb54f7a65",
          "h5_url": "https://tw.news.yahoo.com/share/b514a5f9-7fa6-40ce-a78e-c93bb54f7a65",
          "appIconUrl": "",
          "sourceUniqueId": "content_yahoo",
          "package": ""
        },
        {
          "text": "2026基本工資一次看",
          "url": "https://tw.news.yahoo.com/2026%E5%9F%BA%E6%9C%AC%E5%B7%A5%E8%B3%87%E5%A4%9A%E5%B0%91%EF%BC%9F%E5%B7%A5%E6%99%82%E4%B8%8A%E9%99%90%E7%82%BA%E4%BD%95%EF%BC%9F%E5%8A%A0%E7%8F%AD%E8%B2%BB%E3%80%81%E4%BE%8B%E5%81%87%E4%BC%91%E5%81%87%E6%80%8E%E9%BA%BC%E7%AE%97%EF%BC%9F%E5%8B%9E%E5%9F%BA%E6%B3%95%E5%9F%BA%E6%9C%AC%E6%AC%8A%E7%9B%8A6%E5%A4%A7qa-045213937.html",
          "h5_url": "https://tw.news.yahoo.com/2026%E5%9F%BA%E6%9C%AC%E5%B7%A5%E8%B3%87%E5%A4%9A%E5%B0%91%EF%BC%9F%E5%B7%A5%E6%99%82%E4%B8%8A%E9%99%90%E7%82%BA%E4%BD%95%EF%BC%9F%E5%8A%A0%E7%8F%AD%E8%B2%BB%E3%80%81%E4%BE%8B%E5%81%87%E4%BC%91%E5%81%87%E6%80%8E%E9%BA%BC%E7%AE%97%EF%BC%9F%E5%8B%9E%E5%9F%BA%E6%B3%95%E5%9F%BA%E6%9C%AC%E6%AC%8A%E7%9B%8A6%E5%A4%A7qa-045213937.html",
          "appIconUrl": "",
          "sourceUniqueId": "content_yahoo",
          "package": ""
        },
        {
          "text": "Yahoo財經大人物",
          "url": "https://tw.news.yahoo.com/topic/CEO-interview",
          "h5_url": "https://tw.news.yahoo.com/topic/CEO-interview",
          "appIconUrl": "",
          "sourceUniqueId": "content_yahoo",
          "package": ""
        },
        {
          "text": "Yahoo Tech",
          "url": "https://tw.news.yahoo.com/yahoo_tech_tw_942--%E6%89%80%E6%9C%89%E9%A1%9E%E5%88%A5/archive",
          "h5_url": "https://tw.news.yahoo.com/yahoo_tech_tw_942--%E6%89%80%E6%9C%89%E9%A1%9E%E5%88%A5/archive",
          "appIconUrl": "",
          "sourceUniqueId": "content_yahoo",
          "package": ""
        },
        {
          "text": "2025搜尋大數據揭密",
          "url": "https://tw.news.yahoo.com/12%E5%80%8B%E6%84%8F%E6%83%B3%E4%B8%8D%E5%88%B0%E5%8F%B0%E7%81%A3%E4%BA%BA%E7%9A%84%E6%90%9C%E5%B0%8B%E8%A1%8C%E7%82%BA-%E6%98%9F%E6%9C%9F%E4%B8%80%E6%83%B3%E9%9B%A2%E8%81%B7%EF%BC%9F%E6%98%9F%E6%9C%9F%E4%BA%8C%E8%A8%82%E6%A9%9F%E7%A5%A8%EF%BC%9F%EF%BD%9Cyahoo-2025%E6%90%9C%E5%B0%8B%E5%A4%A7%E6%95%B8%E6%93%9A%E6%8F%AD%E5%AF%86-020000000.html",
          "h5_url": "https://tw.news.yahoo.com/12%E5%80%8B%E6%84%8F%E6%83%B3%E4%B8%8D%E5%88%B0%E5%8F%B0%E7%81%A3%E4%BA%BA%E7%9A%84%E6%90%9C%E5%B0%8B%E8%A1%8C%E7%82%BA-%E6%98%9F%E6%9C%9F%E4%B8%80%E6%83%B3%E9%9B%A2%E8%81%B7%EF%BC%9F%E6%98%9F%E6%9C%9F%E4%BA%8C%E8%A8%82%E6%A9%9F%E7%A5%A8%EF%BC%9F%EF%BD%9Cyahoo-2025%E6%90%9C%E5%B0%8B%E5%A4%A7%E6%95%B8%E6%93%9A%E6%8F%AD%E5%AF%86-020000000.html",
          "appIconUrl": "",
          "sourceUniqueId": "content_yahoo",
          "package": ""
        },
        {
          "text": "新年快樂！各地煙火迎接2026",
          "url": "https://tw.news.yahoo.com/2026%E8%B7%A8%E5%B9%B4%E7%85%99%E7%81%AB%E5%90%84%E7%B8%A3%E5%B8%82%E7%9B%B4%E6%92%AD%EF%BC%9A%E5%8F%B0%E5%8C%97101%E3%80%81%E5%8F%B0%E4%B8%AD%E9%BA%97%E5%AF%B6%E3%80%81%E9%AB%98%E9%9B%84%E5%A4%A2%E6%99%82%E4%BB%A3%E3%80%81%E5%AE%9C%E8%8A%B1%E6%9D%B1%E3%80%81%E6%96%B0%E5%8C%97%E6%B7%A1%E6%B0%B412%E7%B8%A3%E5%B8%82%E4%B8%80%E6%AC%A1%E7%9C%8B-010537874.html",
          "h5_url": "https://tw.news.yahoo.com/2026%E8%B7%A8%E5%B9%B4%E7%85%99%E7%81%AB%E5%90%84%E7%B8%A3%E5%B8%82%E7%9B%B4%E6%92%AD%EF%BC%9A%E5%8F%B0%E5%8C%97101%E3%80%81%E5%8F%B0%E4%B8%AD%E9%BA%97%E5%AF%B6%E3%80%81%E9%AB%98%E9%9B%84%E5%A4%A2%E6%99%82%E4%BB%A3%E3%80%81%E5%AE%9C%E8%8A%B1%E6%9D%B1%E3%80%81%E6%96%B0%E5%8C%97%E6%B7%A1%E6%B0%B412%E7%B8%A3%E5%B8%82%E4%B8%80%E6%AC%A1%E7%9C%8B-010537874.html",
          "appIconUrl": "",
          "sourceUniqueId": "content_yahoo",
          "package": ""
        },
        {
          "text": "住院逾一年 陳菊傳農曆年後回歸",
          "url": "https://tw.news.yahoo.com/%E7%8D%A8-%E8%AB%8B%E8%BE%AD%E6%9C%AA%E7%8D%B2%E5%87%86-%E5%82%B3%E9%99%B3%E8%8F%8A%E8%BE%B2%E6%9B%86%E5%B9%B4%E5%89%8D%E5%87%BA%E9%99%A2-%E5%B9%B4%E5%BE%8C%E5%9B%9E%E5%B4%97%E4%BD%8D%E4%B8%8A%E7%8F%AD-140250164.html",
          "h5_url": "https://tw.news.yahoo.com/%E7%8D%A8-%E8%AB%8B%E8%BE%AD%E6%9C%AA%E7%8D%B2%E5%87%86-%E5%82%B3%E9%99%B3%E8%8F%8A%E8%BE%B2%E6%9B%86%E5%B9%B4%E5%89%8D%E5%87%BA%E9%99%A2-%E5%B9%B4%E5%BE%8C%E5%9B%9E%E5%B4%97%E4%BD%8D%E4%B8%8A%E7%8F%AD-140250164.html",
          "appIconUrl": "",
          "sourceUniqueId": "content_yahoo",
          "package": ""
        },
        {
          "text": "元旦愈晚愈冷 這波估探10℃以下",
          "url": "https://tw.news.yahoo.com/%E6%98%8E%E5%A4%A9%E5%A4%A9%E6%B0%A3%E5%86%B7%E6%B0%A3%E5%9C%98%E5%8D%97%E4%B8%8B-%E5%85%83%E6%97%A6%E6%84%88%E6%99%9A%E6%84%88%E5%86%B7-%E5%91%A8%E4%BA%94%E4%B8%AD%E9%83%A8%E4%BB%A5%E5%8C%97%E4%BD%8E%E6%BA%AB%E6%81%90%E4%B8%8D%E5%88%B010%E2%84%83-095649753.html",
          "h5_url": "https://tw.news.yahoo.com/%E6%98%8E%E5%A4%A9%E5%A4%A9%E6%B0%A3%E5%86%B7%E6%B0%A3%E5%9C%98%E5%8D%97%E4%B8%8B-%E5%85%83%E6%97%A6%E6%84%88%E6%99%9A%E6%84%88%E5%86%B7-%E5%91%A8%E4%BA%94%E4%B8%AD%E9%83%A8%E4%BB%A5%E5%8C%97%E4%BD%8E%E6%BA%AB%E6%81%90%E4%B8%8D%E5%88%B010%E2%84%83-095649753.html",
          "appIconUrl": "",
          "sourceUniqueId": "content_yahoo",
          "package": ""
        },
        {
          "text": "路透：陸企訂逾200萬顆輝達H200",
          "url": "https://tw.news.yahoo.com/%E8%B7%AF%E9%80%8F-%E8%BC%9D%E9%81%94%E7%8D%B2%E4%B8%AD%E4%BC%81%E4%B8%8B%E8%A8%82200%E8%90%AC%E9%A4%98%E9%A1%86h200-%E5%B7%B2%E6%B4%BD%E5%8F%B0%E7%A9%8D%E9%9B%BB%E5%A2%9E%E7%94%A2-092842608.html",
          "h5_url": "https://tw.news.yahoo.com/%E8%B7%AF%E9%80%8F-%E8%BC%9D%E9%81%94%E7%8D%B2%E4%B8%AD%E4%BC%81%E4%B8%8B%E8%A8%82200%E8%90%AC%E9%A4%98%E9%A1%86h200-%E5%B7%B2%E6%B4%BD%E5%8F%B0%E7%A9%8D%E9%9B%BB%E5%A2%9E%E7%94%A2-092842608.html",
          "appIconUrl": "",
          "sourceUniqueId": "content_yahoo",
          "package": ""
        },
        {
          "text": "兒遭輾亡 父：本來要跟同學跨年",
          "url": "https://tw.news.yahoo.com/%E9%A9%9A%E6%82%9A%E7%9E%AC%E9%96%93%E7%95%AB%E9%9D%A2%E6%9B%9D-%E9%AB%98%E9%9B%8421%E6%AD%B2%E9%A8%8E%E5%A3%AB%E9%81%AD%E8%B2%A8%E8%BB%8A%E8%BC%BE%E6%96%83-%E7%88%B6%E6%AF%8D%E6%82%B2%E6%B3%A3-%E6%9C%AC%E4%BE%86%E8%A6%81%E8%B7%9F%E5%90%8C%E5%AD%B8%E8%B7%A8%E5%B9%B4-131000607.html",
          "h5_url": "https://tw.news.yahoo.com/%E9%A9%9A%E6%82%9A%E7%9E%AC%E9%96%93%E7%95%AB%E9%9D%A2%E6%9B%9D-%E9%AB%98%E9%9B%8421%E6%AD%B2%E9%A8%8E%E5%A3%AB%E9%81%AD%E8%B2%A8%E8%BB%8A%E8%BC%BE%E6%96%83-%E7%88%B6%E6%AF%8D%E6%82%B2%E6%B3%A3-%E6%9C%AC%E4%BE%86%E8%A6%81%E8%B7%9F%E5%90%8C%E5%AD%B8%E8%B7%A8%E5%B9%B4-131000607.html",
          "appIconUrl": "",
          "sourceUniqueId": "content_yahoo",
          "package": ""
        },
        {
          "text": "高院判3年6月定讞 蔡正元將入獄",
          "url": "https://tw.news.yahoo.com/%E8%94%A1%E6%AD%A3%E5%85%83%E6%B6%89%E6%A5%AD%E5%8B%99%E4%BE%B5%E5%8D%A0%E7%BD%AA-%E9%AB%98%E9%99%A2%E5%88%A4%E5%88%913%E5%B9%B46%E6%9C%88%E5%AE%9A%E8%AE%9E-112717100.html",
          "h5_url": "https://tw.news.yahoo.com/%E8%94%A1%E6%AD%A3%E5%85%83%E6%B6%89%E6%A5%AD%E5%8B%99%E4%BE%B5%E5%8D%A0%E7%BD%AA-%E9%AB%98%E9%99%A2%E5%88%A4%E5%88%913%E5%B9%B46%E6%9C%88%E5%AE%9A%E8%AE%9E-112717100.html",
          "appIconUrl": "",
          "sourceUniqueId": "content_yahoo",
          "package": ""
        },
        {
          "text": "郵局大廳變產房 人牆守護畫面暖",
          "url": "https://tw.news.yahoo.com/%E5%BD%B0%E5%8C%9623%E6%AD%B2%E5%AD%95%E5%A9%A6%E8%B7%91%E9%83%B5%E5%B1%80%E7%AA%81%E7%BE%8A%E6%B0%B4%E7%A0%B4%E8%A3%82-%E6%95%91%E8%AD%B7%E5%93%A1-%E5%8E%9F%E5%9C%B0%E6%8E%A5%E7%94%9F-%E4%BA%BA%E7%89%86%E5%AE%88%E8%AD%B7%E5%AF%B6%E5%AF%B6%E8%AA%95%E7%94%9F-081600290.html",
          "h5_url": "https://tw.news.yahoo.com/%E5%BD%B0%E5%8C%9623%E6%AD%B2%E5%AD%95%E5%A9%A6%E8%B7%91%E9%83%B5%E5%B1%80%E7%AA%81%E7%BE%8A%E6%B0%B4%E7%A0%B4%E8%A3%82-%E6%95%91%E8%AD%B7%E5%93%A1-%E5%8E%9F%E5%9C%B0%E6%8E%A5%E7%94%9F-%E4%BA%BA%E7%89%86%E5%AE%88%E8%AD%B7%E5%AF%B6%E5%AF%B6%E8%AA%95%E7%94%9F-081600290.html",
          "appIconUrl": "",
          "sourceUniqueId": "content_yahoo",
          "package": ""
        },
        {
          "text": "「生平第一次被起訴」趙少康認罪",
          "url": "https://tw.news.yahoo.com/%E5%A4%A7%E7%BD%B7%E5%85%8D%E4%BA%AE%E7%A5%A8%E8%A2%AB%E8%A8%B4-%E8%B6%99%E5%B0%91%E5%BA%B7%E8%AA%8D%E7%BD%AA%E9%82%84%E6%80%AA%E8%A8%98%E8%80%85%E9%80%B2%E7%AE%A1%E5%88%B6%E5%8D%80-%E8%87%AA%E8%AA%8D-%E7%8A%AF%E5%BE%8C%E6%85%8B%E5%BA%A6%E5%A5%BD-%E6%B1%82%E7%B7%A9%E5%88%91-083854549.html",
          "h5_url": "https://tw.news.yahoo.com/%E5%A4%A7%E7%BD%B7%E5%85%8D%E4%BA%AE%E7%A5%A8%E8%A2%AB%E8%A8%B4-%E8%B6%99%E5%B0%91%E5%BA%B7%E8%AA%8D%E7%BD%AA%E9%82%84%E6%80%AA%E8%A8%98%E8%80%85%E9%80%B2%E7%AE%A1%E5%88%B6%E5%8D%80-%E8%87%AA%E8%AA%8D-%E7%8A%AF%E5%BE%8C%E6%85%8B%E5%BA%A6%E5%A5%BD-%E6%B1%82%E7%B7%A9%E5%88%91-083854549.html",
          "appIconUrl": "",
          "sourceUniqueId": "content_yahoo",
          "package": ""
        },
        {
          "text": "病假不能沒收全勤 1月新制整理",
          "url": "https://tw.news.yahoo.com/1%E6%9C%88%E6%96%B0%E5%88%B6%E6%87%B6%E4%BA%BA%E5%8C%85%EF%BC%9A%E6%9C%80%E4%BD%8E%E5%B7%A5%E8%B3%87%E6%BC%B2%E8%87%B32%E8%90%AC9500%E5%85%83%E3%80%81%E7%94%9F%E8%82%B2%E8%A3%9C%E5%8A%A9%E6%AF%8F%E8%83%8E10%E8%90%AC%E3%80%81%E7%97%85%E5%81%87%E9%82%84%E6%9C%89%E5%85%A8%E5%8B%A4%E6%8B%BF-020730504.html",
          "h5_url": "https://tw.news.yahoo.com/1%E6%9C%88%E6%96%B0%E5%88%B6%E6%87%B6%E4%BA%BA%E5%8C%85%EF%BC%9A%E6%9C%80%E4%BD%8E%E5%B7%A5%E8%B3%87%E6%BC%B2%E8%87%B32%E8%90%AC9500%E5%85%83%E3%80%81%E7%94%9F%E8%82%B2%E8%A3%9C%E5%8A%A9%E6%AF%8F%E8%83%8E10%E8%90%AC%E3%80%81%E7%97%85%E5%81%87%E9%82%84%E6%9C%89%E5%85%A8%E5%8B%A4%E6%8B%BF-020730504.html",
          "appIconUrl": "",
          "sourceUniqueId": "content_yahoo",
          "package": ""
        },
        {
          "text": "中共環台軍演 日本政府曝立場",
          "url": "https://tw.news.yahoo.com/%E4%B8%AD%E5%85%B1%E7%92%B0%E5%8F%B0%E8%BB%8D%E6%BC%94-%E6%97%A5%E6%9C%AC%E6%94%BF%E5%BA%9C%E8%A1%A8%E6%85%8B%EF%BC%9A%E5%8F%B0%E6%B5%B7%E5%92%8C%E5%B9%B3%E7%A9%A9%E5%AE%9A%E5%B0%8D%E5%9C%8B%E9%9A%9B%E8%87%B3%E9%97%9C%E9%87%8D%E8%A6%81-073211130.html",
          "h5_url": "https://tw.news.yahoo.com/%E4%B8%AD%E5%85%B1%E7%92%B0%E5%8F%B0%E8%BB%8D%E6%BC%94-%E6%97%A5%E6%9C%AC%E6%94%BF%E5%BA%9C%E8%A1%A8%E6%85%8B%EF%BC%9A%E5%8F%B0%E6%B5%B7%E5%92%8C%E5%B9%B3%E7%A9%A9%E5%AE%9A%E5%B0%8D%E5%9C%8B%E9%9A%9B%E8%87%B3%E9%97%9C%E9%87%8D%E8%A6%81-073211130.html",
          "appIconUrl": "",
          "sourceUniqueId": "content_yahoo",
          "package": ""
        }
      ],
      "selectedStatus": false,
      "rank_type": "rank_ahoo"
    },
    {
      "track_id": "hq_google",
      "title": "Google",
      "title_icon_url": "",
      "headImageUrl": "",
      "link_type": "app",
      "data": [
        {
          "text": "中共軍演濫扯「主權」 陸委會：中華民國存在115年",
          "url": "https://news.google.com/rss/articles/CBMiXkFVX3lxTE5GX1p2NlpBRGJUYlROS0RXT3J3cE81cGFHd2FNWnBLa1Nmem1ZODVwQzdCNnF3OTdRcjJqRHpSdWpmdU9oZ2VmdEwxWWQ4dDlRVUljd1E2dWM1bkplUnc?oc=5",
          "h5_url": "https://news.google.com/rss/articles/CBMiXkFVX3lxTE5GX1p2NlpBRGJUYlROS0RXT3J3cE81cGFHd2FNWnBLa1Nmem1ZODVwQzdCNnF3OTdRcjJqRHpSdWpmdU9oZ2VmdEwxWWQ4dDlRVUljd1E2dWM1bkplUnc?oc=5",
          "appIconUrl": "",
          "sourceUniqueId": "content_google",
          "package": ""
        },
        {
          "text": "廚餘機每台補助5000元 台中宣布1/2起開放申請",
          "url": "https://news.google.com/rss/articles/CBMiqAJBVV95cUxNSmN4NzZjVHF0eHFFdFhGUDhfNFo3LWNlRjMwUWtSX2R6aGJuWXVrT2RiRlZiY0lHNHcxak83Mi1XOFUyUzVYSVlHZm5vc25PT3VWM0pFN2hTWENyM0NDV1Q5VWVLY0pNcUllaFk0MVRGaTNvSFVpeFBhckhMYkhrcEYzTkZ2NEs5akRZR0VlSnFyUmtZOGNyV1RtWUo1WTRmcmZRMkVZUFU3X3poV0IybF9KLXpaZ1ZGbWJlZHJaTWZydlhmdjQwZ2pRQ3I1Tms4Z04yc0FVaUVxNFJlelAwcXNfT3pBdkdWSkQwclNFS0FQRWFkZXB1QXdSbmhOQ1J2c0NmQXdZQ2V3dW1SYlB5ZFk1UUZCLVBHdGRnaEt4YVp4N1had2lwcA?oc=5",
          "h5_url": "https://news.google.com/rss/articles/CBMiqAJBVV95cUxNSmN4NzZjVHF0eHFFdFhGUDhfNFo3LWNlRjMwUWtSX2R6aGJuWXVrT2RiRlZiY0lHNHcxak83Mi1XOFUyUzVYSVlHZm5vc25PT3VWM0pFN2hTWENyM0NDV1Q5VWVLY0pNcUllaFk0MVRGaTNvSFVpeFBhckhMYkhrcEYzTkZ2NEs5akRZR0VlSnFyUmtZOGNyV1RtWUo1WTRmcmZRMkVZUFU3X3poV0IybF9KLXpaZ1ZGbWJlZHJaTWZydlhmdjQwZ2pRQ3I1Tms4Z04yc0FVaUVxNFJlelAwcXNfT3pBdkdWSkQwclNFS0FQRWFkZXB1QXdSbmhOQ1J2c0NmQXdZQ2V3dW1SYlB5ZFk1UUZCLVBHdGRnaEt4YVp4N1had2lwcA?oc=5",
          "appIconUrl": "",
          "sourceUniqueId": "content_google",
          "package": ""
        },
        {
          "text": "勞保條例修正案三讀通過 勞動部：3面向保障勞工權益",
          "url": "https://news.google.com/rss/articles/CBMiX0FVX3lxTE10SEtKZzFvZk82dHlUWV9nbWlaLXgzVVFHQWJRbG14YXVkeTRxR1VzVXZmYXY2b2JxMm1FTDVadGwwNGtTZ215cndodk40aU11ZVRjLWpkMlhZV2VfWU9V0gFkQVVfeXFMUDYyZUNDYV9fWmRaTktQRlkwekNVVE4tODlfbnNqM3d6ZDQyREpxNDhUMFZtejYtbkkzNmF1dE45dGVZdWlTcEt0QUlIV1d4X0VLcXNFY1V6UGtyczBfMHQ4V2ZvMA?oc=5",
          "h5_url": "https://news.google.com/rss/articles/CBMiX0FVX3lxTE10SEtKZzFvZk82dHlUWV9nbWlaLXgzVVFHQWJRbG14YXVkeTRxR1VzVXZmYXY2b2JxMm1FTDVadGwwNGtTZ215cndodk40aU11ZVRjLWpkMlhZV2VfWU9V0gFkQVVfeXFMUDYyZUNDYV9fWmRaTktQRlkwekNVVE4tODlfbnNqM3d6ZDQyREpxNDhUMFZtejYtbkkzNmF1dE45dGVZdWlTcEt0QUlIV1d4X0VLcXNFY1V6UGtyczBfMHQ4V2ZvMA?oc=5",
          "appIconUrl": "",
          "sourceUniqueId": "content_google",
          "package": ""
        },
        {
          "text": "台股2025年亮麗封關!台積電ADR盤前勁揚 台指期夜盤續漲",
          "url": "https://news.google.com/rss/articles/CBMi4wJBVV95cUxQYkp4SFNkMG9NQzZiTWpQT09UVTJfTTdlUTBra1M1b1paZDdLdVdiUHBHcmliUWR3Z2JKM0syay1PMVlfZUhNMEJhcmV6WjY4amR6cmJFUmdNOVJZUU5YQlJ5RTljd2tLUV9ybUgtYWVJNjE4TkdqcTM5RnZQVGtsZzhVQkVUODFRSFZmRVRLVndHSEZqR0dqbW1VLXh0SWNHbHlwVDc4Y0VXaGQtYVpLNGxlLUMzRHIzM3Z0MXlKM0VsNXFoN09hMndhLUo5YzRyd21yTlBKd09vV09iVlY3LVcxRmxidHV3VUNmNHpaNTIyVDZsQ3Y5bzc1Ni1GRFlCY2VWZHo2MEYxV05PUmg3Xy0xOUk0aGNRd05ORG1uZURYdHFJcXBjTTVoNGVtSk9IR3F4N2VhdWV1Z0tSd3p1QkJWU0NxVGR0bnhZLVgxSnU0aHFyLUNBQTVXM3BjQjJiUTJV?oc=5",
          "h5_url": "https://news.google.com/rss/articles/CBMi4wJBVV95cUxQYkp4SFNkMG9NQzZiTWpQT09UVTJfTTdlUTBra1M1b1paZDdLdVdiUHBHcmliUWR3Z2JKM0syay1PMVlfZUhNMEJhcmV6WjY4amR6cmJFUmdNOVJZUU5YQlJ5RTljd2tLUV9ybUgtYWVJNjE4TkdqcTM5RnZQVGtsZzhVQkVUODFRSFZmRVRLVndHSEZqR0dqbW1VLXh0SWNHbHlwVDc4Y0VXaGQtYVpLNGxlLUMzRHIzM3Z0MXlKM0VsNXFoN09hMndhLUo5YzRyd21yTlBKd09vV09iVlY3LVcxRmxidHV3VUNmNHpaNTIyVDZsQ3Y5bzc1Ni1GRFlCY2VWZHo2MEYxV05PUmg3Xy0xOUk0aGNRd05ORG1uZURYdHFJcXBjTTVoNGVtSk9IR3F4N2VhdWV1Z0tSd3p1QkJWU0NxVGR0bnhZLVgxSnU0aHFyLUNBQTVXM3BjQjJiUTJV?oc=5",
          "appIconUrl": "",
          "sourceUniqueId": "content_google",
          "package": ""
        },
        {
          "text": "中小學導師加給每月增至4000元、鐘點費提高20% 溯自9/1生效",
          "url": "https://news.google.com/rss/articles/CBMiX0FVX3lxTFB3c3gzMjJOaTMxM2VoQkNTYjNEZFVvMzE2VE00YjN2clJjX20zYnhvbGFLUDJ0YldjMERxMVNMMkh3OVVKMG10TWxydDRNcjdWTURxX1VnVDNmQzhIdEdz?oc=5",
          "h5_url": "https://news.google.com/rss/articles/CBMiX0FVX3lxTFB3c3gzMjJOaTMxM2VoQkNTYjNEZFVvMzE2VE00YjN2clJjX20zYnhvbGFLUDJ0YldjMERxMVNMMkh3OVVKMG10TWxydDRNcjdWTURxX1VnVDNmQzhIdEdz?oc=5",
          "appIconUrl": "",
          "sourceUniqueId": "content_google",
          "package": ""
        },
        {
          "text": "海巡艦監控驅離中國海警船管碧玲：台灣海域唯一執法者",
          "url": "https://news.google.com/rss/articles/CBMiX0FVX3lxTE9YX2llRTlUMkVqWkxVSlg1aGRrRUFJVXMyRjl4aWdOSUt5M0V4Wm9BQmFERnMzNTFIOHFDZm5WcTRfRWdhUzBncUc3b2p2Q0xmaG9STkIzR0tDNThDX2E4?oc=5",
          "h5_url": "https://news.google.com/rss/articles/CBMiX0FVX3lxTE9YX2llRTlUMkVqWkxVSlg1aGRrRUFJVXMyRjl4aWdOSUt5M0V4Wm9BQmFERnMzNTFIOHFDZm5WcTRfRWdhUzBncUc3b2p2Q0xmaG9STkIzR0tDNThDX2E4?oc=5",
          "appIconUrl": "",
          "sourceUniqueId": "content_google",
          "package": ""
        },
        {
          "text": "跨年賞煙火要帶傘！元旦強烈大陸冷氣團來襲 低溫下探6度時間點曝光",
          "url": "https://news.google.com/rss/articles/CBMiUEFVX3lxTE5lWnNpcnluZFhjQWx6SElwQkJFNXpjczg0VTFFNF83OVVFcEQxcWhtTDk3Z19fS0ZEbUQxUzVKaXF0S241VmpZZkF2VnlWQTZw0gFWQVVfeXFMT01jRHFOYkhweXl3Q0gtQnFXT3lUdFNKVHp6MmJ3YnNFRnlkTFZZUjF5Nnd6R0M5bGRzTTRaNXF3N1Y5MkZyT2gwZ2tzWGc3X3lPZGRLb1E?oc=5",
          "h5_url": "https://news.google.com/rss/articles/CBMiUEFVX3lxTE5lWnNpcnluZFhjQWx6SElwQkJFNXpjczg0VTFFNF83OVVFcEQxcWhtTDk3Z19fS0ZEbUQxUzVKaXF0S241VmpZZkF2VnlWQTZw0gFWQVVfeXFMT01jRHFOYkhweXl3Q0gtQnFXT3lUdFNKVHp6MmJ3YnNFRnlkTFZZUjF5Nnd6R0M5bGRzTTRaNXF3N1Y5MkZyT2gwZ2tzWGc3X3lPZGRLb1E?oc=5",
          "appIconUrl": "",
          "sourceUniqueId": "content_google",
          "package": ""
        },
        {
          "text": "2026台北跨年晚會交通攻略 捷運2站進站免費、管制措施一次掌握【互動地圖】",
          "url": "https://news.google.com/rss/articles/CBMiX0FVX3lxTE5EMnY4Y25SS2tCekYwMExXOV9mbjdEamN5MHRHQ1N0MnJaN2F0WS1RdHlQaFRaVGE2SFZoWUtNRHQ5T1pGWjhrUHJaMWdDZWw3TEJid2FWcTRQREx6UFBZ?oc=5",
          "h5_url": "https://news.google.com/rss/articles/CBMiX0FVX3lxTE5EMnY4Y25SS2tCekYwMExXOV9mbjdEamN5MHRHQ1N0MnJaN2F0WS1RdHlQaFRaVGE2SFZoWUtNRHQ5T1pGWjhrUHJaMWdDZWw3TEJid2FWcTRQREx6UFBZ?oc=5",
          "appIconUrl": "",
          "sourceUniqueId": "content_google",
          "package": ""
        },
        {
          "text": "迎接2025最美煙火夜！臺北3處河濱賞101、新北20:26跨河煙火閃耀星空",
          "url": "https://news.google.com/rss/articles/CBMiXkFVX3lxTE5ySTFodHhuNGlZbmJzVW9vWXdtMFQ4ZUliY3JOTFI1dEpBQTE0anpVUUgzWVo4OTd4OE8wMVJaY0VmdGluTWF4eEx2VzFJR3liYUNxT3dZRlh0ck5TOEE?oc=5",
          "h5_url": "https://news.google.com/rss/articles/CBMiXkFVX3lxTE5ySTFodHhuNGlZbmJzVW9vWXdtMFQ4ZUliY3JOTFI1dEpBQTE0anpVUUgzWVo4OTd4OE8wMVJaY0VmdGluTWF4eEx2VzFJR3liYUNxT3dZRlh0ck5TOEE?oc=5",
          "appIconUrl": "",
          "sourceUniqueId": "content_google",
          "package": ""
        },
        {
          "text": "2026台中跨年演唱會卡司！告五人＆動力火車熱情開唱，180秒煙火施放、表演出場順序、直播資訊一次看！",
          "url": "https://news.google.com/rss/articles/CBMilgFBVV95cUxONlA0Ni1KVnJpbFh0TW1SZWlSbTFOeU11WmFaY1RHUWtiWTlpQl9sbTBSNjJlM2tfWl9oUzlLOHRWY1dhSFBZRUhjTmJMeUxCZmJUSUxmVG1pbnJtWHU3YlNtRTFxOGN3cmxFWDd0S2VGSENpeEZOang0MVJzMU00YjgzWlY1WHVDem10QV9GRmhlb1RMLUE?oc=5",
          "h5_url": "https://news.google.com/rss/articles/CBMilgFBVV95cUxONlA0Ni1KVnJpbFh0TW1SZWlSbTFOeU11WmFaY1RHUWtiWTlpQl9sbTBSNjJlM2tfWl9oUzlLOHRWY1dhSFBZRUhjTmJMeUxCZmJUSUxmVG1pbnJtWHU3YlNtRTFxOGN3cmxFWDd0S2VGSENpeEZOang0MVJzMU00YjgzWlY1WHVDem10QV9GRmhlb1RMLUE?oc=5",
          "appIconUrl": "",
          "sourceUniqueId": "content_google",
          "package": ""
        },
        {
          "text": "2026跨年煙火各國直播一次看：澳洲雪梨21:00登場、紐西蘭、台北101、泰國曼谷、杜拜哈里發塔、時代廣場",
          "url": "https://news.google.com/rss/articles/CBMi2wRBVV95cUxQTXI1ck5nWkhVMkQ2N3BhZFFhNW02dW04Xzh1eTRDZzNncXJZbGJWd0JHaS1YN3VsWjVJblRWbUpNcUpKVlJSa3pwZmgwcUk3TjhqclFDQnc3MTh5b29zOHQ3WUNrWm1rMlNkV1NUZTFVWHpob1JyWnpmeENyZ1VGaURRZWFLb0NxeHk3ckFiU0cyMlFsQjZleDJQZDF4OTAtZ1VpVFpVZnY0UFRWSGJsVnpnOFA0Q28tYU1fQVZCcnB1Vm5aVkhZX2phN0pZMkhzaVI2NWZ3ZEY0OVlkZUlkX2FOZGVyZjY0NjdwWTlyX2RkNVk3RERrWW5PR2RWYThnSnFmc241akNiUDB6TVE5aFNpNV9DWGRiMm8yYVJXTkw2YjNMUmUyV3FnWWhhM2pVSGUyWG9WOXk5YzY5cGhMMUVhdFdYbkU2WXlfUG1ybjdRaFBheDJlZ0ZLTWp6ZURHbkNzRGhsNXBfVkdUWFZOVHJLZGZmSF9pSW95N01VQWxzY0Jra3hxekxaTktVVWxxa1FBM1JrSEphMlBZZzR5alhiWHVvSXFHLTJ6NEdaSEdta3NYdGFYRWFaLVlCcWZ1bFZ5b2dWby12ZHA5S2Q2U3BPb3pLWWFFNG5DSkkxZkFIaHJkblJ4LWhTWXdLZGhZYk1LbG1UU1ZnMlc5a2ZQa2tUZW1nczVxSHhKZjFpSDhWTnNURjZlVWlrZUJGWjNqZUJveDBhanVuZ1Q5Rmt6MXFsODFKYURQVThrMjBJeTBLYmNyYlduazhjVDg4MkEtSHJqVW84RmRNYTg?oc=5",
          "h5_url": "https://news.google.com/rss/articles/CBMi2wRBVV95cUxQTXI1ck5nWkhVMkQ2N3BhZFFhNW02dW04Xzh1eTRDZzNncXJZbGJWd0JHaS1YN3VsWjVJblRWbUpNcUpKVlJSa3pwZmgwcUk3TjhqclFDQnc3MTh5b29zOHQ3WUNrWm1rMlNkV1NUZTFVWHpob1JyWnpmeENyZ1VGaURRZWFLb0NxeHk3ckFiU0cyMlFsQjZleDJQZDF4OTAtZ1VpVFpVZnY0UFRWSGJsVnpnOFA0Q28tYU1fQVZCcnB1Vm5aVkhZX2phN0pZMkhzaVI2NWZ3ZEY0OVlkZUlkX2FOZGVyZjY0NjdwWTlyX2RkNVk3RERrWW5PR2RWYThnSnFmc241akNiUDB6TVE5aFNpNV9DWGRiMm8yYVJXTkw2YjNMUmUyV3FnWWhhM2pVSGUyWG9WOXk5YzY5cGhMMUVhdFdYbkU2WXlfUG1ybjdRaFBheDJlZ0ZLTWp6ZURHbkNzRGhsNXBfVkdUWFZOVHJLZGZmSF9pSW95N01VQWxzY0Jra3hxekxaTktVVWxxa1FBM1JrSEphMlBZZzR5alhiWHVvSXFHLTJ6NEdaSEdta3NYdGFYRWFaLVlCcWZ1bFZ5b2dWby12ZHA5S2Q2U3BPb3pLWWFFNG5DSkkxZkFIaHJkblJ4LWhTWXdLZGhZYk1LbG1UU1ZnMlc5a2ZQa2tUZW1nczVxSHhKZjFpSDhWTnNURjZlVWlrZUJGWjNqZUJveDBhanVuZ1Q5Rmt6MXFsODFKYURQVThrMjBJeTBLYmNyYlduazhjVDg4MkEtSHJqVW84RmRNYTg?oc=5",
          "appIconUrl": "",
          "sourceUniqueId": "content_google",
          "package": ""
        },
        {
          "text": "川普火大 澤倫斯基否認襲普亭官邸",
          "url": "https://news.google.com/rss/articles/CBMiU0FVX3lxTE82Z0JsNTZtd3lLT3RPcHljUW0tc3Nrd3lKRnJlSVNYb09UNS1Pa2o5WjQzT3RBb3JtV29OTEh4T0ZVUGtONldDQzlfbnpqcVpGcmsw0gFYQVVfeXFMT19aa0YzQjBKS3J3MXNGZ2k3RmVEcWUxWlpUTjhOcmpBNWNvUVBtYldidHQ3cVBmT2JWY1F1MVZoRTR6SjYyWmhtSlhURFpLb0FiRUVIcFJGbw?oc=5",
          "h5_url": "https://news.google.com/rss/articles/CBMiU0FVX3lxTE82Z0JsNTZtd3lLT3RPcHljUW0tc3Nrd3lKRnJlSVNYb09UNS1Pa2o5WjQzT3RBb3JtV29OTEh4T0ZVUGtONldDQzlfbnpqcVpGcmsw0gFYQVVfeXFMT19aa0YzQjBKS3J3MXNGZ2k3RmVEcWUxWlpUTjhOcmpBNWNvUVBtYldidHQ3cVBmT2JWY1F1MVZoRTR6SjYyWmhtSlhURFpLb0FiRUVIcFJGbw?oc=5",
          "appIconUrl": "",
          "sourceUniqueId": "content_google",
          "package": ""
        },
        {
          "text": "提「台灣有事」引中日關係緊張共同社：高市早苗上任後頻會外交官員| 國際焦點",
          "url": "https://news.google.com/rss/articles/CBMiUEFVX3lxTE5NU1dJUWMtcjc3Z1NYUnNUdjJkWFlQMUFDbWxVUG5tZk81RGRHLXlxOFF5NlVsbjQ2TVI0RnFpb1dhbXdLdHVLcFljS0pvMGdx?oc=5",
          "h5_url": "https://news.google.com/rss/articles/CBMiUEFVX3lxTE5NU1dJUWMtcjc3Z1NYUnNUdjJkWFlQMUFDbWxVUG5tZk81RGRHLXlxOFF5NlVsbjQ2TVI0RnFpb1dhbXdLdHVLcFljS0pvMGdx?oc=5",
          "appIconUrl": "",
          "sourceUniqueId": "content_google",
          "package": ""
        },
        {
          "text": "新／日本一小時內連5震！最大規模5.6 未發布海嘯警報",
          "url": "https://news.google.com/rss/articles/CBMiU0FVX3lxTFAxQlh3Ty1DQjVvaE1xb3pSOWNqVDQxSk1FaXREbGJoZno4WFhsNmc4TVN2eElodDBZdWdIYUIyUlNra2dpZUFiYTEtVEdrWWRCekhr?oc=5",
          "h5_url": "https://news.google.com/rss/articles/CBMiU0FVX3lxTFAxQlh3Ty1DQjVvaE1xb3pSOWNqVDQxSk1FaXREbGJoZno4WFhsNmc4TVN2eElodDBZdWdIYUIyUlNra2dpZUFiYTEtVEdrWWRCekhr?oc=5",
          "appIconUrl": "",
          "sourceUniqueId": "content_google",
          "package": ""
        },
        {
          "text": "報導：中國科技公司下單逾200萬顆H200晶片 輝達緊急洽談台積電擴產",
          "url": "https://news.google.com/rss/articles/CBMiT0FVX3lxTE5VeUNjUTJRMUU1MVFNZC1uNnB2YkxabHU0bndCcDFwM05ZclN5eFB5WmJtOVdnNTMxT0FhRXA2NFpqbjNEbmhqdTZrYUQ3ZzA?oc=5",
          "h5_url": "https://news.google.com/rss/articles/CBMiT0FVX3lxTE5VeUNjUTJRMUU1MVFNZC1uNnB2YkxabHU0bndCcDFwM05ZclN5eFB5WmJtOVdnNTMxT0FhRXA2NFpqbjNEbmhqdTZrYUQ3ZzA?oc=5",
          "appIconUrl": "",
          "sourceUniqueId": "content_google",
          "package": ""
        }
      ],
      "selectedStatus": false,
      "rank_type": "rank_google"
    }
  ],
  "hash": "c2d15b8822404d2ea10f48b759eadba1",
  "qt": "composite_ad_yahoo_google",
  "message": "success",
  "cost": 21,
  "status": 0
}